Workbook

Sheet Guide
A1: K-pop idol sim: economy, growth and revenue model
A3: What each tab does
A4: Inputs: numbers every tab shares (Roblox cut, DevEx rate, gems per pull, pity, event length, regions where paid random items are restricted).
A5: Pacing: upgrade costs, zones and walls. How long free and paying players wait at each point, checked against targets.
A6: Gems: free gem income, Robux gem bundles, and what it costs to reach pity sooner.
A7: Odds: pull odds (the exact numbers the game must show), odds with a luck boost on, pity maths, and the average cost of each chase item.
A8: Revenue: the chance a new player buys each item, revenue per player, a monthly projection and a sensitivity grid.
A9: Growth: 26 weeks of new players (organic, friends, off-Roblox content, ads, comebacks), a retention heat map by install week, Creator Rewards, and whether ads pay back.
A10: Heat maps: revenue by product and player age, and planned play time by feature and player age.
A11: Tracking: the analytics events to log so these heat maps fill with real data after launch.
A13: Colours
A14: Blue text = an input you can change. Black text = calculated. Green text = pulled from another tab.
... A28: Rewarded video ads (Roblox only offers them to games with 100K+ average daily players), trading, and day-by-day timing inside a week.

Sheet Inputs
A1: Shared inputs
A2: Blue = change me. Yellow = check this, or replace it with real data.
A4: Input | B4: Value | C4: Unit | D4: Note / source
A5: DevEx rate (cash you get per Robux you exchange) | B5: 0.0038 | C5: USD per Robux | D5: Roblox Creator Docs, "Earn on Roblox": 10,000 Robux = $38.
A6: Your share of Robux from in-game sales | B6: 0.7 | C6: % | D6: Roblox Creator Docs: creators generally earn 70% of what they sell in Robux in their game.
A7: What a player pays per Robux | B7: 0.0125 | C7: USD per Robux | D7: About $9.99 for 800 Robux. Varies by package, platform and country.
A8: Gems per single pull | B8: 100 | C8: gems | D8: Design choice.
A9: Pity: Center or better guaranteed by pull # | B9: 60 | C9: pulls | D9: Design choice.
A10: Comeback (event) length | B10: 21 | C10: days | D10: Design choice.
A11: Minutes an engaged player plays per day | B11: 45 | C11: minutes | D11: Placeholder. Replace with average session length x sessions per day.
A12: Share of your players where paid random items are restricted | B12: 0.15 | C12: % | D12: Roblox names Australia, Belgium, Netherlands, UK and Brazil as regulated markets (DevForum, May 2026). Placeholder share: check players by country in Creator Analytics.
A13: Restricted players buy pack-related items at this share of the normal rate | B13: 0.3 | C13: % | D13: They cannot buy packs with Robux-bought gems, but may still buy boosts for earned packs. Placeholder.
A15: Calculated
A16: Of every $1 a player spends, you keep | B16: =B6*B5/B7 -> 0.2128 | C16: % | D16: After Roblox's 30% and the DevEx exchange rate.

Sheet Pacing
A1: Pacing: fast early, slower later
A2: Each upgrade costs more than the last and boosts Hype a little. Entering a zone means paying a wall, then Hype jumps. Simulated for active play only.
A4: Upgrade inputs
A5: Hype per click at start | B5: 1 | C5: Design choice.
A6: Clicks per second while playing | B6: 4 | C6: Average including pauses. Placeholder.
A7: First upgrade cost (Hype) | B7: 12 | C7: Design choice.
A8: Each upgrade boosts Hype by | B8: 0.1 | C8: Multiplies: 10 upgrades = 1.1^10 = 2.6x.
A9: Payer owns 2x Hype? (1 = yes, 0 = no) | B9: 1 | C9: Scenario switch for the payer columns.
A10: Payer owns Auto-Stream? (1 = yes, 0 = no) | B10: 1 | C10: Scenario switch for the payer columns.
A11: Auto-Stream speed vs. clicking by hand | B11: 1.25 | C11: Placeholder: auto-clicks a bit faster than a person keeps up.
A12: Payer Hype multiplier | B12: =IF(B9=1,2,1)*IF(B10=1,B11,1) -> 2.5 | C12: Applies to every payer column below.
A14: Zone | B14: Name | C14: Starts at upgrade # | D14: Cost growth per upgrade | E14: Hype boost on entry | F14: Wall (x that upgrade's cost) | G14: Total Hype multiplier | H14: Unlock cost (Hype) | I14: Free player arrives (min played) | J14: Free player arrives (day) | K14: Payer arrives (min played) | L14: Payer is faster by | M14: Wall wait, free player (min)
A15: 1 | B15: Practice Room | C15: 1 | D15: 1.18 | E15: 1 | F15: 0 | G15: =E15 -> 1 | H15: =IF(A15=1,0,INDEX($E$53:$E$172,C15)) -> 0 | I15: =IF(A15=1,0,INDEX($I$53:$I$172,C15)) -> 0 | J15: =IF(A15=1,1,MAX(1,ROUNDUP(I15/Inputs!$B$11,0))) -> 1 | K15: =IF(A15=1,0,INDEX($M$53:$M$172,C15)) -> 0 | L15: =IF(A15=1,"-",I15/K15) -> - | M15: =IF(A15=1,0,INDEX($H$53:$H$172,C15)/60) -> 0
A16: 2 | B16: Busking Street | C16: 30 | D16: 1.24 | E16: 2 | F16: 2 | G16: =G15*E16 -> 2 | H16: =IF(A16=1,0,INDEX($E$53:$E$172,C16)) -> 3064.2848 | I16: =IF(A16=1,0,INDEX($I$53:$I$172,C16)) -> 5.7856009 | J16: =IF(A16=1,1,MAX(1,ROUNDUP(I16/Inputs!$B$11,0))) -> 1 | K16: =IF(A16=1,0,INDEX($M$53:$M$172,C16)) -> 2.3142404 | L16: =IF(A16=1,"-",I16/K16) -> 2.5 | M16: =IF(A16=1,0,INDEX($H$53:$H$172,C16)/60) -> 1.2073169
A17: 3 | B17: Showcase Hall | C17: 44 | D17: 1.3 | E17: 1.6 | F17: 6 | G17: =G16*E17 -> 3.2 | H17: =IF(A17=1,0,INDEX($E$53:$E$172,C17)) -> 195828.39 | I17: =IF(A17=1,0,INDEX($I$53:$I$172,C17)) -> 20.364042 | J17: =IF(A17=1,1,MAX(1,ROUNDUP(I17/Inputs!$B$11,0))) -> 1 | K17: =IF(A17=1,0,INDEX($M$53:$M$172,C17)) -> 8.1456167 | L17: =IF(A17=1,"-",I17/K17) -> 2.5 | M17: =IF(A17=1,0,INDEX($H$53:$H$172,C17)/60) -> 7.9012488
A18: 4 | B18: Music Show Stage | C18: 52 | D18: 1.28 | E18: 1.6 | F18: 2 | G18: =G17*E18 -> 5.12 | H18: =IF(A18=1,0,INDEX($E$53:$E$172,C18)) -> 524285.48 | I18: =IF(A18=1,0,INDEX($I$53:$I$172,C18)) -> 38.473872 | J18: =IF(A18=1,1,MAX(1,ROUNDUP(I18/Inputs!$B$11,0))) -> 1 | K18: =IF(A18=1,0,INDEX($M$53:$M$172,C18)) -> 15.389549 | L18: =IF(A18=1,"-",I18/K18) -> 2.5 | M18: =IF(A18=1,0,INDEX($H$53:$H$172,C18)/60) -> 7.9299586
A19: 5 | B19: Fan Meeting Hall | C19: 62 | D19: 1.2 | E19: 1.6 | F19: 1.5 | G19: =G18*E19 -> 8.192 | H19: =IF(A19=1,0,INDEX($E$53:$E$172,C19)) -> 4352112 | I19: =IF(A19=1,0,INDEX($I$53:$I$172,C19)) -> 90.304099 | J19: =IF(A19=1,1,MAX(1,ROUNDUP(I19/Inputs!$B$11,0))) -> 3 | K19: =IF(A19=1,0,INDEX($M$53:$M$172,C19)) -> 36.12164 | L19: =IF(A19=1,"-",I19/K19) -> 2.5 | M19: =IF(A19=1,0,INDEX($H$53:$H$172,C19)/60) -> 17.624379
A20: 6 | B20: Concert Hall | C20: 74 | D20: 1.2 | E20: 1.6 | F20: 1.5 | G20: =G19*E20 -> 13.1072 | H20: =IF(A20=1,0,INDEX($E$53:$E$172,C20)) -> 38803868 | I20: =IF(A20=1,0,INDEX($I$53:$I$172,C20)) -> 206.41681 | J20: =IF(A20=1,1,MAX(1,ROUNDUP(I20/Inputs!$B$11,0))) -> 5 | K20: =IF(A20=1,0,INDEX($M$53:$M$172,C20)) -> 82.566723 | L20: =IF(A20=1,"-",I20/K20) -> 2.5 | M20: =IF(A20=1,0,INDEX($H$53:$H$172,C20)/60) -> 31.293675
A21: 7 | B21: Arena | C21: 86 | D21: 1.2 | E21: 1.6 | F21: 1.5 | G21: =G20*E21 -> 20.97152 | H21: =IF(A21=1,0,INDEX($E$53:$E$172,C21)) -> 3.4597918e+08 | I21: =IF(A21=1,0,INDEX($I$53:$I$172,C21)) -> 412.5854 | J21: =IF(A21=1,1,MAX(1,ROUNDUP(I21/Inputs!$B$11,0))) -> 10 | K21: =IF(A21=1,0,INDEX($M$53:$M$172,C21)) -> 165.03416 | L21: =IF(A21=1,"-",I21/K21) -> 2.5 | M21: =IF(A21=1,0,INDEX($H$53:$H$172,C21)/60) -> 55.564743
A22: 8 | B22: Stadium | C22: 98 | D22: 1.2 | E22: 1.6 | F22: 1.5 | G22: =G21*E22 -> 33.554432 | H22: =IF(A22=1,0,INDEX($E$53:$E$172,C22)) -> 3.0847851e+09 | I22: =IF(A22=1,0,INDEX($I$53:$I$172,C22)) -> 778.65633 | J22: =IF(A22=1,1,MAX(1,ROUNDUP(I22/Inputs!$B$11,0))) -> 18 | K22: =IF(A22=1,0,INDEX($M$53:$M$172,C22)) -> 311.46253 | L22: =IF(A22=1,"-",I22/K22) -> 2.5 | M22: =IF(A22=1,0,INDEX($H$53:$H$172,C22)/60) -> 98.660215
A23: 9 | B23: World Tour | C23: 110 | D23: 1.2 | E23: 1.6 | F23: 1.5 | G23: =G22*E23 -> 53.687091 | H23: =IF(A23=1,0,INDEX($E$53:$E$172,C23)) -> 2.7504254e+10 | I23: =IF(A23=1,0,INDEX($I$53:$I$172,C23)) -> 1428.6483 | J23: =IF(A23=1,1,MAX(1,ROUNDUP(I23/Inputs!$B$11,0))) -> 32 | K23: =IF(A23=1,0,INDEX($M$53:$M$172,C23)) -> 571.45932 | L23: =IF(A23=1,"-",I23/K23) -> 2.5 | M23: =IF(A23=1,0,INDEX($H$53:$H$172,C23)/60) -> 175.18012
A24: Zone 1 has no wall. A wall is a one-time unlock cost; the first big one (Showcase Hall) is where the Debut Pack offer appears.
A25: Does the curve hit the targets?
A26: Phase | B26: From (min played) | C26: To (min played) | D26: Target wait, fastest (sec) | E26: Target wait, slowest (sec) | F26: Actual average wait (sec) | G26: Status
A27: First minute | B27: 0 | C27: 1 | D27: 2 | E27: 8 | F27: =IFERROR(AVERAGEIFS($H$53:$H$172,$I$53:$I$172,">="&B27,$I$53:$I$172,"<"&C27,$C$53:$C$172,0),"none") -> 4.5445524 | G27: =IF(ISNUMBER(F27),IF(F27<D27,"Too fast",IF(F27>E27,"Too slow","OK")),"No upgrades here") -> OK
A28: Minutes 1-5 | B28: 1 | C28: 5 | D28: 8 | E28: 30 | F28: =IFERROR(AVERAGEIFS($H$53:$H$172,$I$53:$I$172,">="&B28,$I$53:$I$172,"<"&C28,$C$53:$C$172,0),"none") -> 12.95073 | G28: =IF(ISNUMBER(F28),IF(F28<D28,"Too fast",IF(F28>E28,"Too slow","OK")),"No upgrades here") -> OK
A29: Minutes 5-15 | B29: 5 | C29: 15 | D29: 25 | E29: 90 | F29: =IFERROR(AVERAGEIFS($H$53:$H$172,$I$53:$I$172,">="&B29,$I$53:$I$172,"<"&C29,$C$53:$C$172,0),"none") -> 30.81781 | G29: =IF(ISNUMBER(F29),IF(F29<D29,"Too fast",IF(F29>E29,"Too slow","OK")),"No upgrades here") -> OK
A30: Minutes 15-30 | B30: 15 | C30: 30 | D30: 60 | E30: 180 | F30: =IFERROR(AVERAGEIFS($H$53:$H$172,$I$53:$I$172,">="&B30,$I$53:$I$172,"<"&C30,$C$53:$C$172,0),"none") -> 79.082689 | G30: =IF(ISNUMBER(F30),IF(F30<D30,"Too fast",IF(F30>E30,"Too slow","OK")),"No upgrades here") -> OK
A31: Minutes 30-60 | B31: 30 | C31: 60 | D31: 120 | E31: 300 | F31: =IFERROR(AVERAGEIFS($H$53:$H$172,$I$53:$I$172,">="&B31,$I$53:$I$172,"<"&C31,$C$53:$C$172,0),"none") -> 168.76382 | G31: =IF(ISNUMBER(F31),IF(F31<D31,"Too fast",IF(F31>E31,"Too slow","OK")),"No upgrades here") -> OK
A32: Hour 1 to day 7 | B32: 60 | C32: =7*Inputs!$B$11 -> 315 | D32: 240 | E32: 600 | F32: =IFERROR(AVERAGEIFS($H$53:$H$172,$I$53:$I$172,">="&B32,$I$53:$I$172,"<"&C32,$C$53:$C$172,0),"none") -> 534.65987 | G32: =IF(ISNUMBER(F32),IF(F32<D32,"Too fast",IF(F32>E32,"Too slow","OK")),"No upgrades here") -> OK
A33: Weeks 2-3 | B33: =C32 -> 315 | C33: =21*Inputs!$B$11 -> 945 | D33: 600 | E33: 1800 | F33: =IFERROR(AVERAGEIFS($H$53:$H$172,$I$53:$I$172,">="&B33,$I$53:$I$172,"<"&C33,$C$53:$C$172,0),"none") -> 1531.2774 | G33: =IF(ISNUMBER(F33),IF(F33<D33,"Too fast",IF(F33>E33,"Too slow","OK")),"No upgrades here") -> OK
A34: Walls are left out of these averages; their waits are in the zone table above.
A36: Where a player is after X minutes of play
A37: Minutes played | B37: Roughly day | C37: Upgrades bought (free) | D37: Zone (free) | E37: Wait for next upgrade (sec, free) | F37: Upgrades bought (payer) | G37: Zone (payer)
A38: 1 | B38: =MAX(1,ROUNDUP(A38/Inputs!$B$11,0)) -> 1 | C38: =IFERROR(MATCH(A38,$I$53:$I$172,1),0) -> 12 | D38: =INDEX($B$15:$B$23,IF(C38=0,1,INDEX($B$53:$B$172,C38))) -> Practice Room | E38: =IF(C38>=ROWS($H$53:$H$172),"-",INDEX($H$53:$H$172,C38+1)) -> 6.9661548 | F38: =IFERROR(MATCH(A38,$M$53:$M$172,1),0) -> 21 | G38: =INDEX($B$15:$B$23,IF(F38=0,1,INDEX($B$53:$B$172,F38))) -> Practice Room
A39: 5 | B39: =MAX(1,ROUNDUP(A39/Inputs!$B$11,0)) -> 1 | C39: =IFERROR(MATCH(A39,$I$53:$I$172,1),0) -> 29 | D39: =INDEX($B$15:$B$23,IF(C39=0,1,INDEX($B$53:$B$172,C39))) -> Practice Room | E39: =IF(C39>=ROWS($H$53:$H$172),"-",INDEX($H$53:$H$172,C39+1)) -> 72.439014 | F39: =IFERROR(MATCH(A39,$M$53:$M$172,1),0) -> 43 | G39: =INDEX($B$15:$B$23,IF(F39=0,1,INDEX($B$53:$B$172,F39))) -> Busking Street
A40: 10 | B40: =MAX(1,ROUNDUP(A40/Inputs!$B$11,0)) -> 1 | C40: =IFERROR(MATCH(A40,$I$53:$I$172,1),0) -> 40 | D40: =INDEX($B$15:$B$23,IF(C40=0,1,INDEX($B$53:$B$172,C40))) -> Busking Street | E40: =IF(C40>=ROWS($H$53:$H$172),"-",INDEX($H$53:$H$172,C40+1)) -> 45.096234 | F40: =IFERROR(MATCH(A40,$M$53:$M$172,1),0) -> 48 | G40: =INDEX($B$15:$B$23,IF(F40=0,1,INDEX($B$53:$B$172,F40))) -> Showcase Hall
A41: 15 | B41: =MAX(1,ROUNDUP(A41/Inputs!$B$11,0)) -> 1 | C41: =IFERROR(MATCH(A41,$I$53:$I$172,1),0) -> 43 | D41: =INDEX($B$15:$B$23,IF(C41=0,1,INDEX($B$53:$B$172,C41))) -> Busking Street | E41: =IF(C41>=ROWS($H$53:$H$172),"-",INDEX($H$53:$H$172,C41+1)) -> 474.07493 | F41: =IFERROR(MATCH(A41,$M$53:$M$172,1),0) -> 51 | G41: =INDEX($B$15:$B$23,IF(F41=0,1,INDEX($B$53:$B$172,F41))) -> Showcase Hall
A42: 30 | B42: =MAX(1,ROUNDUP(A42/Inputs!$B$11,0)) -> 1 | C42: =IFERROR(MATCH(A42,$I$53:$I$172,1),0) -> 50 | D42: =INDEX($B$15:$B$23,IF(C42=0,1,INDEX($B$53:$B$172,C42))) -> Showcase Hall | E42: =IF(C42>=ROWS($H$53:$H$172),"-",INDEX($H$53:$H$172,C42+1)) -> 136.29616 | F42: =IFERROR(MATCH(A42,$M$53:$M$172,1),0) -> 61 | G42: =INDEX($B$15:$B$23,IF(F42=0,1,INDEX($B$53:$B$172,F42))) -> Music Show Stage
A43: 45 | B43: =MAX(1,ROUNDUP(A43/Inputs!$B$11,0)) -> 1 | C43: =IFERROR(MATCH(A43,$I$53:$I$172,1),0) -> 54 | D43: =INDEX($B$15:$B$23,IF(C43=0,1,INDEX($B$53:$B$172,C43))) -> Music Show Stage | E43: =IF(C43>=ROWS($H$53:$H$172),"-",INDEX($H$53:$H$172,C43+1)) -> 156.18265 | F43: =IFERROR(MATCH(A43,$M$53:$M$172,1),0) -> 66 | G43: =INDEX($B$15:$B$23,IF(F43=0,1,INDEX($B$53:$B$172,F43))) -> Fan Meeting Hall
A44: 90 | B44: =MAX(1,ROUNDUP(A44/Inputs!$B$11,0)) -> 2 | C44: =IFERROR(MATCH(A44,$I$53:$I$172,1),0) -> 61 | D44: =INDEX($B$15:$B$23,IF(C44=0,1,INDEX($B$53:$B$172,C44))) -> Music Show Stage | E44: =IF(C44>=ROWS($H$53:$H$172),"-",INDEX($H$53:$H$172,C44+1)) -> 1057.4627 | F44: =IFERROR(MATCH(A44,$M$53:$M$172,1),0) -> 76 | G44: =INDEX($B$15:$B$23,IF(F44=0,1,INDEX($B$53:$B$172,F44))) -> Concert Hall
A45: 135 | B45: =MAX(1,ROUNDUP(A45/Inputs!$B$11,0)) -> 3 | C45: =IFERROR(MATCH(A45,$I$53:$I$172,1),0) -> 69 | D45: =INDEX($B$15:$B$23,IF(C45=0,1,INDEX($B$53:$B$172,C45))) -> Fan Meeting Hall | E45: =IF(C45>=ROWS($H$53:$H$172),"-",INDEX($H$53:$H$172,C45+1)) -> 530.29015 | F45: =IFERROR(MATCH(A45,$M$53:$M$172,1),0) -> 84 | G45: =INDEX($B$15:$B$23,IF(F45=0,1,INDEX($B$53:$B$172,F45))) -> Concert Hall
A46: 225 | B46: =MAX(1,ROUNDUP(A46/Inputs!$B$11,0)) -> 5 | C46: =IFERROR(MATCH(A46,$I$53:$I$172,1),0) -> 76 | D46: =INDEX($B$15:$B$23,IF(C46=0,1,INDEX($B$53:$B$172,C46))) -> Concert Hall | E46: =IF(C46>=ROWS($H$53:$H$172),"-",INDEX($H$53:$H$172,C46+1)) -> 609.41551 | F46: =IFERROR(MATCH(A46,$M$53:$M$172,1),0) -> 93 | G46: =INDEX($B$15:$B$23,IF(F46=0,1,INDEX($B$53:$B$172,F46))) -> Arena
A47: 315 | B47: =MAX(1,ROUNDUP(A47/Inputs!$B$11,0)) -> 7 | C47: =IFERROR(MATCH(A47,$I$53:$I$172,1),0) -> 82 | D47: =INDEX($B$15:$B$23,IF(C47=0,1,INDEX($B$53:$B$172,C47))) -> Concert Hall | E47: =IF(C47>=ROWS($H$53:$H$172),"-",INDEX($H$53:$H$172,C47+1)) -> 1027.176 | F47: =IFERROR(MATCH(A47,$M$53:$M$172,1),0) -> 98 | G47: =INDEX($B$15:$B$23,IF(F47=0,1,INDEX($B$53:$B$172,F47))) -> Stadium
A48: 630 | B48: =MAX(1,ROUNDUP(A48/Inputs!$B$11,0)) -> 14 | C48: =IFERROR(MATCH(A48,$I$53:$I$172,1),0) -> 95 | D48: =INDEX($B$15:$B$23,IF(C48=0,1,INDEX($B$53:$B$172,C48))) -> Arena | E48: =IF(C48>=ROWS($H$53:$H$172),"-",INDEX($H$53:$H$172,C48+1)) -> 1989.6477 | F48: =IFERROR(MATCH(A48,$M$53:$M$172,1),0) -> 112 | G48: =INDEX($B$15:$B$23,IF(F48=0,1,INDEX($B$53:$B$172,F48))) -> World Tour
A49: 945 | B49: =MAX(1,ROUNDUP(A49/Inputs!$B$11,0)) -> 21 | C49: =IFERROR(MATCH(A49,$I$53:$I$172,1),0) -> 103 | D49: =INDEX($B$15:$B$23,IF(C49=0,1,INDEX($B$53:$B$172,C49))) -> Stadium | E49: =IF(C49>=ROWS($H$53:$H$172),"-",INDEX($H$53:$H$172,C49+1)) -> 2494.3919 | F49: =IFERROR(MATCH(A49,$M$53:$M$172,1),0) -> 120 | G49: =INDEX($B$15:$B$23,IF(F49=0,1,INDEX($B$53:$B$172,F49))) -> World Tour
A51: Every upgrade, step by step
A52: Upgrade # | B52: Zone | C52: Wall? (1 = zone unlock) | D52: Upgrade cost (Hype) | E52: Unlock cost (Hype) | F52: Zone while saving | G52: Hype per sec (free) | H52: Wait (sec, free) | I52: Total played (min, free) | J52: Phase | K52: Hype per sec (payer) | L52: Wait (sec, payer) | M52: Total played (min, payer)
A53: 1 | B53: =MATCH(A53,$C$15:$C$23,1) -> 1 | C53: =IF(AND(B53>1,A53=INDEX($C$15:$C$23,B53)),1,0) -> 0 | D53: =$B$7 -> 12 | E53: =C53*INDEX($F$15:$F$23,B53)*D53 -> 0 | F53: =B53 -> 1 | G53: =$B$5*$B$6*(1+$B$8)^(A53-1)*INDEX($G$15:$G$23,F53) -> 4 | H53: =(D53+E53)/G53 -> 3 | I53: =H53/60 -> 0.05 | J53: =IF(I53>=$C$33,"Later",INDEX($A$27:$A$33,MATCH(I53,$B$27:$B$33,1))) -> First minute | K53: =G53*$B$12 -> 10 | L53: =(D53+E53)/K53 -> 1.2 | M53: =L53/60 -> 0.02
A54: 2 | B54: =MATCH(A54,$C$15:$C$23,1) -> 1 | C54: =IF(AND(B54>1,A54=INDEX($C$15:$C$23,B54)),1,0) -> 0 | D54: =D53*INDEX($D$15:$D$23,B54) -> 14.16 | E54: =C54*INDEX($F$15:$F$23,B54)*D54 -> 0 | F54: =B53 -> 1 | G54: =$B$5*$B$6*(1+$B$8)^(A54-1)*INDEX($G$15:$G$23,F54) -> 4.4 | H54: =(D54+E54)/G54 -> 3.2181818 | I54: =I53+H54/60 -> 0.10363636 | J54: =IF(I54>=$C$33,"Later",INDEX($A$27:$A$33,MATCH(I54,$B$27:$B$33,1))) -> First minute | K54: =G54*$B$12 -> 11 | L54: =(D54+E54)/K54 -> 1.2872727 | M54: =M53+L54/60 -> 0.041454545
A55: 3 | B55: =MATCH(A55,$C$15:$C$23,1) -> 1 | C55: =IF(AND(B55>1,A55=INDEX($C$15:$C$23,B55)),1,0) -> 0 | D55: =D54*INDEX($D$15:$D$23,B55) -> 16.7088 | E55: =C55*INDEX($F$15:$F$23,B55)*D55 -> 0 | F55: =B54 -> 1 | G55: =$B$5*$B$6*(1+$B$8)^(A55-1)*INDEX($G$15:$G$23,F55) -> 4.84 | H55: =(D55+E55)/G55 -> 3.4522314 | I55: =I54+H55/60 -> 0.16117355 | J55: =IF(I55>=$C$33,"Later",INDEX($A$27:$A$33,MATCH(I55,$B$27:$B$33,1))) -> First minute | K55: =G55*$B$12 -> 12.1 | L55: =(D55+E55)/K55 -> 1.3808926 | M55: =M54+L55/60 -> 0.064469421
A56: 4 | B56: =MATCH(A56,$C$15:$C$23,1) -> 1 | C56: =IF(AND(B56>1,A56=INDEX($C$15:$C$23,B56)),1,0) -> 0 | D56: =D55*INDEX($D$15:$D$23,B56) -> 19.716384 | E56: =C56*INDEX($F$15:$F$23,B56)*D56 -> 0 | F56: =B55 -> 1 | G56: =$B$5*$B$6*(1+$B$8)^(A56-1)*INDEX($G$15:$G$23,F56) -> 5.324 | H56: =(D56+E56)/G56 -> 3.7033028 | I56: =I55+H56/60 -> 0.22289527 | J56: =IF(I56>=$C$33,"Later",INDEX($A$27:$A$33,MATCH(I56,$B$27:$B$33,1))) -> First minute | K56: =G56*$B$12 -> 13.31 | L56: =(D56+E56)/K56 -> 1.4813211 | M56: =M55+L56/60 -> 0.089158107
A57: 5 | B57: =MATCH(A57,$C$15:$C$23,1) -> 1 | C57: =IF(AND(B57>1,A57=INDEX($C$15:$C$23,B57)),1,0) -> 0 | D57: =D56*INDEX($D$15:$D$23,B57) -> 23.265333 | E57: =C57*INDEX($F$15:$F$23,B57)*D57 -> 0 | F57: =B56 -> 1 | G57: =$B$5*$B$6*(1+$B$8)^(A57-1)*INDEX($G$15:$G$23,F57) -> 5.8564 | H57: =(D57+E57)/G57 -> 3.9726339 | I57: =I56+H57/60 -> 0.28910583 | J57: =IF(I57>=$C$33,"Later",INDEX($A$27:$A$33,MATCH(I57,$B$27:$B$33,1))) -> First minute | K57: =G57*$B$12 -> 14.641 | L57: =(D57+E57)/K57 -> 1.5890536 | M57: =M56+L57/60 -> 0.11564233
A58: 6 | B58: =MATCH(A58,$C$15:$C$23,1) -> 1 | C58: =IF(AND(B58>1,A58=INDEX($C$15:$C$23,B58)),1,0) -> 0 | D58: =D57*INDEX($D$15:$D$23,B58) -> 27.453093 | E58: =C58*INDEX($F$15:$F$23,B58)*D58 -> 0 | F58: =B57 -> 1 | G58: =$B$5*$B$6*(1+$B$8)^(A58-1)*INDEX($G$15:$G$23,F58) -> 6.44204 | H58: =(D58+E58)/G58 -> 4.2615527 | I58: =I57+H58/60 -> 0.36013171 | J58: =IF(I58>=$C$33,"Later",INDEX($A$27:$A$33,MATCH(I58,$B$27:$B$33,1))) -> First minute | K58: =G58*$B$12 -> 16.1051 | L58: =(D58+E58)/K58 -> 1.7046211 | M58: =M57+L58/60 -> 0.14405268
A59: 7 | B59: =MATCH(A59,$C$15:$C$23,1) -> 1 | C59: =IF(AND(B59>1,A59=INDEX($C$15:$C$23,B59)),1,0) -> 0 | D59: =D58*INDEX($D$15:$D$23,B59) -> 32.39465 | E59: =C59*INDEX($F$15:$F$23,B59)*D59 -> 0 | F59: =B58 -> 1 | G59: =$B$5*$B$6*(1+$B$8)^(A59-1)*INDEX($G$15:$G$23,F59) -> 7.086244 | H59: =(D59+E59)/G59 -> 4.5714838 | I59: =I58+H59/60 -> 0.43632311 | J59: =IF(I59>=$C$33,"Later",INDEX($A$27:$A$33,MATCH(I59,$B$27:$B$33,1))) -> First minute | K59: =G59*$B$12 -> 17.71561 | L59: =(D59+E59)/K59 -> 1.8285935 | M59: =M58+L59/60 -> 0.17452924
A60: 8 | B60: =MATCH(A60,$C$15:$C$23,1) -> 1 | C60: =IF(AND(B60>1,A60=INDEX($C$15:$C$23,B60)),1,0) -> 0 | D60: =D59*INDEX($D$15:$D$23,B60) -> 38.225687 | E60: =C60*INDEX($F$15:$F$23,B60)*D60 -> 0 | F60: =B59 -> 1 | G60: =$B$5*$B$6*(1+$B$8)^(A60-1)*INDEX($G$15:$G$23,F60) -> 7.7948684 | H60: =(D60+E60)/G60 -> 4.9039554 | I60: =I59+H60/60 -> 0.5180557 | J60: =IF(I60>=$C$33,"Later",INDEX($A$27:$A$33,MATCH(I60,$B$27:$B$33,1))) -> First minute | K60: =G60*$B$12 -> 19.487171 | L60: =(D60+E60)/K60 -> 1.9615822 | M60: =M59+L60/60 -> 0.20722228
A61: 9 | B61: =MATCH(A61,$C$15:$C$23,1) -> 1 | C61: =IF(AND(B61>1,A61=INDEX($C$15:$C$23,B61)),1,0) -> 0 | D61: =D60*INDEX($D$15:$D$23,B61) -> 45.10631 | E61: =C61*INDEX($F$15:$F$23,B61)*D61 -> 0 | F61: =B60 -> 1 | G61: =$B$5*$B$6*(1+$B$8)^(A61-1)*INDEX($G$15:$G$23,F61) -> 8.5743552 | H61: =(D61+E61)/G61 -> 5.2606067 | I61: =I60+H61/60 -> 0.60573247 | J61: =IF(I61>=$C$33,"Later",INDEX($A$27:$A$33,MATCH(I61,$B$27:$B$33,1))) -> First minute | K61: =G61*$B$12 -> 21.435888 | L61: =(D61+E61)/K61 -> 2.1042427 | M61: =M60+L61/60 -> 0.24229299
A62: 10 | B62: =MATCH(A62,$C$15:$C$23,1) -> 1 | C62: =IF(AND(B62>1,A62=INDEX($C$15:$C$23,B62)),1,0) -> 0 | D62: =D61*INDEX($D$15:$D$23,B62) -> 53.225446 | E62: =C62*INDEX($F$15:$F$23,B62)*D62 -> 0 | F62: =B61 -> 1 | G62: =$B$5*$B$6*(1+$B$8)^(A62-1)*INDEX($G$15:$G$23,F62) -> 9.4317908 | H62: =(D62+E62)/G62 -> 5.6431963 | I62: =I61+H62/60 -> 0.69978575 | J62: =IF(I62>=$C$33,"Later",INDEX($A$27:$A$33,MATCH(I62,$B$27:$B$33,1))) -> First minute | K62: =G62*$B$12 -> 23.579477 | L62: =(D62+E62)/K62 -> 2.2572785 | M62: =M61+L62/60 -> 0.2799143
A63: 11 | B63: =MATCH(A63,$C$15:$C$23,1) -> 1 | C63: =IF(AND(B63>1,A63=INDEX($C$15:$C$23,B63)),1,0) -> 0 | D63: =D62*INDEX($D$15:$D$23,B63) -> 62.806027 | E63: =C63*INDEX($F$15:$F$23,B63)*D63 -> 0 | F63: =B62 -> 1 | G63: =$B$5*$B$6*(1+$B$8)^(A63-1)*INDEX($G$15:$G$23,F63) -> 10.37497 | H63: =(D63+E63)/G63 -> 6.0536105 | I63: =I62+H63/60 -> 0.80067925 | J63: =IF(I63>=$C$33,"Later",INDEX($A$27:$A$33,MATCH(I63,$B$27:$B$33,1))) -> First minute | K63: =G63*$B$12 -> 25.937425 | L63: =(D63+E63)/K63 -> 2.4214442 | M63: =M62+L63/60 -> 0.3202717
A64: 12 | B64: =MATCH(A64,$C$15:$C$23,1) -> 1 | C64: =IF(AND(B64>1,A64=INDEX($C$15:$C$23,B64)),1,0) -> 0 | D64: =D63*INDEX($D$15:$D$23,B64) -> 74.111111 | E64: =C64*INDEX($F$15:$F$23,B64)*D64 -> 0 | F64: =B63 -> 1 | G64: =$B$5*$B$6*(1+$B$8)^(A64-1)*INDEX($G$15:$G$23,F64) -> 11.412467 | H64: =(D64+E64)/G64 -> 6.4938731 | I64: =I63+H64/60 -> 0.90891047 | J64: =IF(I64>=$C$33,"Later",INDEX($A$27:$A$33,MATCH(I64,$B$27:$B$33,1))) -> First minute | K64: =G64*$B$12 -> 28.531167 | L64: =(D64+E64)/K64 -> 2.5975492 | M64: =M63+L64/60 -> 0.36356419
A65: 13 | B65: =MATCH(A65,$C$15:$C$23,1) -> 1 | C65: =IF(AND(B65>1,A65=INDEX($C$15:$C$23,B65)),1,0) -> 0 | D65: =D64*INDEX($D$15:$D$23,B65) -> 87.451112 | E65: =C65*INDEX($F$15:$F$23,B65)*D65 -> 0 | F65: =B64 -> 1 | G65: =$B$5*$B$6*(1+$B$8)^(A65-1)*INDEX($G$15:$G$23,F65) -> 12.553714 | H65: =(D65+E65)/G65 -> 6.9661548 | I65: =I64+H65/60 -> 1.0250131 | J65: =IF(I65>=$C$33,"Later",INDEX($A$27:$A$33,MATCH(I65,$B$27:$B$33,1))) -> Minutes 1-5 | K65: =G65*$B$12 -> 31.384284 | L65: =(D65+E65)/K65 -> 2.7864619 | M65: =M64+L65/60 -> 0.41000522
... A172: 120 | B172: =MATCH(A172,$C$15:$C$23,1) -> 9 | C172: =IF(AND(B172>1,A172=INDEX($C$15:$C$23,B172)),1,0) -> 0 | D172: =D171*INDEX($D$15:$D$23,B172) -> 1.1353273e+11 | E172: =C172*INDEX($F$15:$F$23,B172)*D172 -> 0 | F172: =B171 -> 9 | G172: =$B$5*$B$6*(1+$B$8)^(A172-1)*INDEX($G$15:$G$23,F172) -> 18099201 | H172: =(D172+E172)/G172 -> 6272.8034 | I172: =I171+H172/60 -> 2157.6686 | J172: =IF(I172>=$C$33,"Later",INDEX($A$27:$A$33,MATCH(I172,$B$27:$B$33,1))) -> Later | K172: =G172*$B$12 -> 45248002 | L172: =(D172+E172)/K172 -> 2509.1214 | M172: =M171+L172/60 -> 863.06745

Sheet Gems
A1: Gems: free income, bundles and pity
A2: Gems are the one premium currency: bought with Robux, or earned slowly by playing. Packs bought with gems count as paid random items.
A4: Free gems an engaged free player earns per day
A5: Attendance calendar (average per day) | B5: 50
A6: Three daily quests | B6: 75
A7: Weekly quests (per-day share) | B7: 40
A8: Achievements and small events (per-day average) | B8: 25
A9: Stage and boss drops | B9: 150
A10: Daily cap on stage and boss gems | B10: 120 | C10: The cap keeps bought gems valuable without limiting play time.
A11: Free gems per day | B11: =SUM(B5:B8)+MIN(B9,B10) -> 310
A12: Gems per pull | B12: =Inputs!$B$8 -> 100
A13: Free pulls per day | B13: =B11/B12 -> 3.1
A14: Pity at pull # | B14: =Inputs!$B$9 -> 60
A15: Days for a free player to reach pity | B15: =B14*B12/B11 -> 19.354839
A16: Comeback length (days) | B16: =Inputs!$B$10 -> 21
A17: Free pulls over one comeback | B17: =B11*B16/B12 -> 65.1
A18: Check | B18: =IF(B15<=B16,"OK: free players reach pity within one comeback","Too slow: free players miss pity this comeback") -> OK: free players reach pity within one comeback
A20: Gem bundles (bought with Robux)
A21: Base gems per Robux (before bonus) | B21: 2
A23: Bundle | B23: Price (Robux) | C23: Bonus gems | D23: Gems | E23: Gems per Robux | F23: Robux per pull | G23: Player pays (USD, approx.) | H23: Gems on first purchase (2x)
A24: Handful | B24: 99 | C24: 0 | D24: =ROUND(B24*$B$21*(1+C24),-1) -> 200 | E24: =D24/B24 -> 2.020202 | F24: =Inputs!$B$8/E24 -> 49.5 | G24: =B24*Inputs!$B$7 -> 1.2375 | H24: =D24*2 -> 400
A25: Pouch | B25: 249 | C25: 0.1 | D25: =ROUND(B25*$B$21*(1+C25),-1) -> 550 | E25: =D25/B25 -> 2.2088353 | F25: =Inputs!$B$8/E25 -> 45.272727 | G25: =B25*Inputs!$B$7 -> 3.1125 | H25: =D25*2 -> 1100
A26: Bag | B26: 499 | C26: 0.15 | D26: =ROUND(B26*$B$21*(1+C26),-1) -> 1150 | E26: =D26/B26 -> 2.3046092 | F26: =Inputs!$B$8/E26 -> 43.391304 | G26: =B26*Inputs!$B$7 -> 6.2375 | H26: =D26*2 -> 2300
A27: Box | B27: 999 | C27: 0.2 | D27: =ROUND(B27*$B$21*(1+C27),-1) -> 2400 | E27: =D27/B27 -> 2.4024024 | F27: =Inputs!$B$8/E27 -> 41.625 | G27: =B27*Inputs!$B$7 -> 12.4875 | H27: =D27*2 -> 4800
A28: Chest | B28: 2499 | C28: 0.25 | D28: =ROUND(B28*$B$21*(1+C28),-1) -> 6250 | E28: =D28/B28 -> 2.5010004 | F28: =Inputs!$B$8/E28 -> 39.984 | G28: =B28*Inputs!$B$7 -> 31.2375 | H28: =D28*2 -> 12500
A29: Vault | B29: 4999 | C29: 0.3 | D29: =ROUND(B29*$B$21*(1+C29),-1) -> 13000 | E29: =D29/B29 -> 2.6005201 | F29: =Inputs!$B$8/E29 -> 38.453846 | G29: =B29*Inputs!$B$7 -> 62.4875 | H29: =D29*2 -> 26000
A31: Bundle used for Robux estimates | B31: Box
A32: Gems per Robux at that bundle | B32: =INDEX($E$24:$E$29,MATCH(B31,$A$24:$A$29,0)) -> 2.4024024
A34: Paying to reach pity sooner (player saves free gems, buys the rest)
A35: Reach pity on day | B35: Free gems saved by then | C35: Gems still needed | D35: Robux to buy them | E35: Player pays (USD, approx.)
A36: 1 | B36: =MIN(A36*$B$11,$B$14*$B$12) -> 310 | C36: =MAX(0,$B$14*$B$12-B36) -> 5690 | D36: =ROUNDUP(C36/$B$32,0) -> 2369 | E36: =D36*Inputs!$B$7 -> 29.6125
A37: 3 | B37: =MIN(A37*$B$11,$B$14*$B$12) -> 930 | C37: =MAX(0,$B$14*$B$12-B37) -> 5070 | D37: =ROUNDUP(C37/$B$32,0) -> 2111 | E37: =D37*Inputs!$B$7 -> 26.3875
A38: 7 | B38: =MIN(A38*$B$11,$B$14*$B$12) -> 2170 | C38: =MAX(0,$B$14*$B$12-B38) -> 3830 | D38: =ROUNDUP(C38/$B$32,0) -> 1595 | E38: =D38*Inputs!$B$7 -> 19.9375
A39: 10 | B39: =MIN(A39*$B$11,$B$14*$B$12) -> 3100 | C39: =MAX(0,$B$14*$B$12-B39) -> 2900 | D39: =ROUNDUP(C39/$B$32,0) -> 1208 | E39: =D39*Inputs!$B$7 -> 15.1
A40: 14 | B40: =MIN(A40*$B$11,$B$14*$B$12) -> 4340 | C40: =MAX(0,$B$14*$B$12-B40) -> 1660 | D40: =ROUNDUP(C40/$B$32,0) -> 691 | E40: =D40*Inputs!$B$7 -> 8.6375
A41: 21 | B41: =MIN(A41*$B$11,$B$14*$B$12) -> 6000 | C41: =MAX(0,$B$14*$B$12-B41) -> 0 | D41: =ROUNDUP(C41/$B$32,0) -> 0 | E41: =D41*Inputs!$B$7 -> 0
A42: This is what you sell: the same reward, sooner. Free players still get there by playing.

Sheet Odds
A1: Pull odds: the game must show exactly these numbers
A2: Roblox rule (May 2026): show each outcome's odds as numbers that add up to 100% before purchase; every outcome must give something; restricted players need a non-random option.
A4: Rarity | B4: Tier | C4: Chance per pull | D4: 1 in... | E4: Chance in one 10-pull | F4: ="Chance in "&Inputs!$B$9&" pulls (ignoring pity)" -> Chance in 60 pulls (ignoring pity) | G4: Luck boost applies? | H4: Chance with a luck boost on
A5: Trainee | B5: Common | C5: 0.6 | D5: =1/C5 -> 1.6666667 | E5: =1-(1-C5)^10 -> 0.99989514 | F5: =1-(1-C5)^Inputs!$B$9 -> 1 | G5: Takes the rest | H5: =1-SUM(H6:H9) -> 0.54
A6: Rookie | B6: Rare | C6: 0.28 | D6: =1/C6 -> 3.5714286 | E6: =1-(1-C6)^10 -> 0.96256094 | F6: =1-(1-C6)^Inputs!$B$9 -> 1 | G6: No | H6: =IF(G6="Yes",C6*$B$11,C6) -> 0.28
A7: Idol | B7: Epic | C7: 0.09 | D7: =1/C7 -> 11.111111 | E7: =1-(1-C7)^10 -> 0.61058388 | F7: =1-(1-C7)^Inputs!$B$9 -> 0.99651275 | G7: Yes | H7: =IF(G7="Yes",C7*$B$11,C7) -> 0.135
A8: Center | B8: Legendary | C8: 0.025 | D8: =1/C8 -> 40 | E8: =1-(1-C8)^10 -> 0.22367038 | F8: =1-(1-C8)^Inputs!$B$9 -> 0.78108428 | G8: Yes | H8: =IF(G8="Yes",C8*$B$11,C8) -> 0.0375
A9: Daesang | B9: Mythic | C9: 0.005 | D9: =1/C9 -> 200 | E9: =1-(1-C9)^10 -> 0.04888987 | F9: =1-(1-C9)^Inputs!$B$9 -> 0.25973904 | G9: Yes | H9: =IF(G9="Yes",C9*$B$11,C9) -> 0.0075
A10: Total | C10: =SUM(C5:C9) -> 1 | D10: =IF(ROUND(C10,6)=1,"OK","Must add up to 100%") -> OK | H10: =SUM(H5:H9) -> 1
A11: Luck boost multiplier (Lucky pass, potion or Concert Boost on) | B11: 1.5
A12: Boost check | B12: =IF(H5>=0,"OK: boosted odds still add up to 100%","Boost too big: Trainee odds fell below zero") -> OK: boosted odds still add up to 100%
A13: While a boost is on, the odds shown in game must switch to the boosted column. Pity must be shown as a number too (e.g. "Center or better by pull 60").
A15: Special version | B15: Chance on any pull | C15: Note
A16: Holo | B16: 0.05 | C16: Rolled separately from rarity. Also made by fusing 5 copies.
A17: Signed | B17: 0.005 | C17: Rolled separately from rarity. Also made by fusing 5 Holos.
A19: Pity
A20: Center or better guaranteed by pull # | B20: =Inputs!$B$9 -> 60
A21: Chance per pull of Center or better | B21: =C8+C9 -> 0.03
A22: Chance pity is needed (no Center+ before it) | B22: =(1-B21)^(B20-1) -> 0.16578007
A23: Average pulls per Center or better (with pity) | B23: =(1-(1-B21)^B20)/B21 -> 27.973111
A25: Most Robux one chase item should cost on average | B25: 10000 | C25: Above this, make it earnable (fusion, events, achievements) rather than pull-only.
A26: Gems per Robux used (Gems tab) | B26: =Gems!$B$32 -> 2.4024024
A28: Chasing | B28: Chance per pull | C28: Average pulls | D28: Average gems | E28: Average Robux | F28: Player pays (USD, approx.) | G28: Verdict
A29: Center or better (with pity) | B29: =B21 -> 0.03 | C29: =B23 -> 27.973111 | D29: =C29*Inputs!$B$8 -> 2797.3111 | E29: =D29/$B$26 -> 1164.3807 | F29: =E29*Inputs!$B$7 -> 14.554759 | G29: =IF(E29<=$B$25,"OK to sell in packs","Too costly: make it earnable") -> OK to sell in packs
A30: Daesang | B30: =C9 -> 0.005 | C30: =1/B30 -> 200 | D30: =C30*Inputs!$B$8 -> 20000 | E30: =D30/$B$26 -> 8325 | F30: =E30*Inputs!$B$7 -> 104.0625 | G30: =IF(E30<=$B$25,"OK to sell in packs","Too costly: make it earnable") -> OK to sell in packs
A31: Holo Center | B31: =C8*B16 -> 0.00125 | C31: =1/B31 -> 800 | D31: =C31*Inputs!$B$8 -> 80000 | E31: =D31/$B$26 -> 33300 | F31: =E31*Inputs!$B$7 -> 416.25 | G31: =IF(E31<=$B$25,"OK to sell in packs","Too costly: make it earnable") -> Too costly: make it earnable
A32: Holo Daesang | B32: =C9*B16 -> 0.00025 | C32: =1/B32 -> 4000 | D32: =C32*Inputs!$B$8 -> 400000 | E32: =D32/$B$26 -> 166500 | F32: =E32*Inputs!$B$7 -> 2081.25 | G32: =IF(E32<=$B$25,"OK to sell in packs","Too costly: make it earnable") -> Too costly: make it earnable
A33: Signed Center | B33: =C8*B17 -> 0.000125 | C33: =1/B33 -> 8000 | D33: =C33*Inputs!$B$8 -> 800000 | E33: =D33/$B$26 -> 333000 | F33: =E33*Inputs!$B$7 -> 4162.5 | G33: =IF(E33<=$B$25,"OK to sell in packs","Too costly: make it earnable") -> Too costly: make it earnable
A34: Signed Daesang | B34: =C9*B17 -> 2.5e-05 | C34: =1/B34 -> 40000 | D34: =C34*Inputs!$B$8 -> 4000000 | E34: =D34/$B$26 -> 1665000 | F34: =E34*Inputs!$B$7 -> 20812.5 | G34: =IF(E34<=$B$25,"OK to sell in packs","Too costly: make it earnable") -> Too costly: make it earnable

Sheet Revenue
A1: Revenue per player (first 30 days)
A2: Every rate here is a placeholder guess, not a benchmark. Replace the yellow cells with Creator Analytics numbers after launch.
A4: Players
A5: New players in the cohort | B5: 1000
A6: Still playing on day 1 | B6: 0.25
A7: Still playing on day 7 | B7: 0.08
A8: Still playing on day 30 | B8: 0.03
A9: Check | B9: =IF(AND(B6>=B7,B7>=B8,B8>0),"OK","Day 1 must be >= day 7 >= day 30 > 0") -> OK
A11: Stage | B11: Share of new players
A12: New | B12: 1
A13: Day 1 | B13: =B6 -> 0.25
A14: Day 7 | B14: =B7 -> 0.08
A15: Day 30 | B15: =B8 -> 0.03
A17: Product | B17: Type | C17: Pack-related? (restricted in some regions) | D17: Price (Robux) | E17: Offered to | F17: Players at that stage | G17: Chance one of them buys | H17: Chance after regional limits | I17: Buys per buyer (30 days) | J17: Chance a new player buys | K17: Buyers | L17: Robux players spend | M17: Robux you receive | N17: Your cash after DevEx (USD) | O17: Share of your revenue
A18: Debut Pack (fixed contents, no randomness) | B18: One-time offer | C18: No | D18: 99 | E18: New | F18: =$B$5*INDEX($B$12:$B$15,MATCH(E18,$A$12:$A$15,0)) -> 1000 | G18: 0.015 | H18: =G18*IF(C18="Yes",1-Inputs!$B$12*(1-Inputs!$B$13),1) -> 0.015 | I18: 1 | J18: =F18/$B$5*H18 -> 0.015 | K18: =F18*H18 -> 15 | L18: =K18*I18*D18 -> 1485 | M18: =L18*Inputs!$B$6 -> 1039.5 | N18: =M18*Inputs!$B$5 -> 3.9501 | O18: =IF($B$47=0,0,N18/$B$47) -> 0.050556688
A19: Auto-Stream | B19: Gamepass | C19: No | D19: 199 | E19: Day 1 | F19: =$B$5*INDEX($B$12:$B$15,MATCH(E19,$A$12:$A$15,0)) -> 250 | G19: 0.04 | H19: =G19*IF(C19="Yes",1-Inputs!$B$12*(1-Inputs!$B$13),1) -> 0.04 | I19: 1 | J19: =F19/$B$5*H19 -> 0.01 | K19: =F19*H19 -> 10 | L19: =K19*I19*D19 -> 1990 | M19: =L19*Inputs!$B$6 -> 1393 | N19: =M19*Inputs!$B$5 -> 5.2934 | O19: =IF($B$47=0,0,N19/$B$47) -> 0.067749366
A20: 2x Hype | B20: Gamepass | C20: No | D20: 149 | E20: Day 1 | F20: =$B$5*INDEX($B$12:$B$15,MATCH(E20,$A$12:$A$15,0)) -> 250 | G20: 0.03 | H20: =G20*IF(C20="Yes",1-Inputs!$B$12*(1-Inputs!$B$13),1) -> 0.03 | I20: 1 | J20: =F20/$B$5*H20 -> 0.0075 | K20: =F20*H20 -> 7.5 | L20: =K20*I20*D20 -> 1117.5 | M20: =L20*Inputs!$B$6 -> 782.25 | N20: =M20*Inputs!$B$5 -> 2.97255 | O20: =IF($B$47=0,0,N20/$B$47) -> 0.038045184
A21: 3x Open | B21: Gamepass | C21: Yes | D21: 249 | E21: Day 1 | F21: =$B$5*INDEX($B$12:$B$15,MATCH(E21,$A$12:$A$15,0)) -> 250 | G21: 0.02 | H21: =G21*IF(C21="Yes",1-Inputs!$B$12*(1-Inputs!$B$13),1) -> 0.0179 | I21: 1 | J21: =F21/$B$5*H21 -> 0.004475 | K21: =F21*H21 -> 4.475 | L21: =K21*I21*D21 -> 1114.275 | M21: =L21*Inputs!$B$6 -> 779.9925 | N21: =M21*Inputs!$B$5 -> 2.9639715 | O21: =IF($B$47=0,0,N21/$B$47) -> 0.037935389
A22: Offline earnings 24h | B22: Gamepass | C22: No | D22: 149 | E22: Day 1 | F22: =$B$5*INDEX($B$12:$B$15,MATCH(E22,$A$12:$A$15,0)) -> 250 | G22: 0.015 | H22: =G22*IF(C22="Yes",1-Inputs!$B$12*(1-Inputs!$B$13),1) -> 0.015 | I22: 1 | J22: =F22/$B$5*H22 -> 0.00375 | K22: =F22*H22 -> 3.75 | L22: =K22*I22*D22 -> 558.75 | M22: =L22*Inputs!$B$6 -> 391.125 | N22: =M22*Inputs!$B$5 -> 1.486275 | O22: =IF($B$47=0,0,N22/$B$47) -> 0.019022592
A23: Gem bundle (average) | B23: Developer product | C23: Yes | D23: 499 | E23: Day 1 | F23: =$B$5*INDEX($B$12:$B$15,MATCH(E23,$A$12:$A$15,0)) -> 250 | G23: 0.03 | H23: =G23*IF(C23="Yes",1-Inputs!$B$12*(1-Inputs!$B$13),1) -> 0.02685 | I23: 2.5 | J23: =F23/$B$5*H23 -> 0.0067125 | K23: =F23*H23 -> 6.7125 | L23: =K23*I23*D23 -> 8373.8438 | M23: =L23*Inputs!$B$6 -> 5861.6906 | N23: =M23*Inputs!$B$5 -> 22.274424 | O23: =IF($B$47=0,0,N23/$B$47) -> 0.28508674
A24: Luck potion | B24: Developer product | C24: Yes | D24: 49 | E24: Day 1 | F24: =$B$5*INDEX($B$12:$B$15,MATCH(E24,$A$12:$A$15,0)) -> 250 | G24: 0.02 | H24: =G24*IF(C24="Yes",1-Inputs!$B$12*(1-Inputs!$B$13),1) -> 0.0179 | I24: 4 | J24: =F24/$B$5*H24 -> 0.004475 | K24: =F24*H24 -> 4.475 | L24: =K24*I24*D24 -> 877.1 | M24: =L24*Inputs!$B$6 -> 613.97 | N24: =M24*Inputs!$B$5 -> 2.333086 | O24: =IF($B$47=0,0,N24/$B$47) -> 0.029860788
A25: Card shop: pick the exact card (no randomness) | B25: Developer product | C25: No | D25: 299 | E25: Day 1 | F25: =$B$5*INDEX($B$12:$B$15,MATCH(E25,$A$12:$A$15,0)) -> 250 | G25: 0.02 | H25: =G25*IF(C25="Yes",1-Inputs!$B$12*(1-Inputs!$B$13),1) -> 0.02 | I25: 1.5 | J25: =F25/$B$5*H25 -> 0.005 | K25: =F25*H25 -> 5 | L25: =K25*I25*D25 -> 2242.5 | M25: =L25*Inputs!$B$6 -> 1569.75 | N25: =M25*Inputs!$B$5 -> 5.96505 | O25: =IF($B$47=0,0,N25/$B$47) -> 0.076345705
A26: 8x Open | B26: Gamepass | C26: Yes | D26: 799 | E26: Day 7 | F26: =$B$5*INDEX($B$12:$B$15,MATCH(E26,$A$12:$A$15,0)) -> 80 | G26: 0.03 | H26: =G26*IF(C26="Yes",1-Inputs!$B$12*(1-Inputs!$B$13),1) -> 0.02685 | I26: 1 | J26: =F26/$B$5*H26 -> 0.002148 | K26: =F26*H26 -> 2.148 | L26: =K26*I26*D26 -> 1716.252 | M26: =L26*Inputs!$B$6 -> 1201.3764 | N26: =M26*Inputs!$B$5 -> 4.5652303 | O26: =IF($B$47=0,0,N26/$B$47) -> 0.058429641
A27: Lucky | B27: Gamepass | C27: Yes | D27: 349 | E27: Day 7 | F27: =$B$5*INDEX($B$12:$B$15,MATCH(E27,$A$12:$A$15,0)) -> 80 | G27: 0.04 | H27: =G27*IF(C27="Yes",1-Inputs!$B$12*(1-Inputs!$B$13),1) -> 0.0358 | I27: 1 | J27: =F27/$B$5*H27 -> 0.002864 | K27: =F27*H27 -> 2.864 | L27: =K27*I27*D27 -> 999.536 | M27: =L27*Inputs!$B$6 -> 699.6752 | N27: =M27*Inputs!$B$5 -> 2.6587658 | O27: =IF($B$47=0,0,N27/$B$47) -> 0.034029111
A28: +1 Squad Slot | B28: Gamepass | C28: No | D28: 299 | E28: Day 7 | F28: =$B$5*INDEX($B$12:$B$15,MATCH(E28,$A$12:$A$15,0)) -> 80 | G28: 0.04 | H28: =G28*IF(C28="Yes",1-Inputs!$B$12*(1-Inputs!$B$13),1) -> 0.04 | I28: 1 | J28: =F28/$B$5*H28 -> 0.0032 | K28: =F28*H28 -> 3.2 | L28: =K28*I28*D28 -> 956.8 | M28: =L28*Inputs!$B$6 -> 669.76 | N28: =M28*Inputs!$B$5 -> 2.545088 | O28: =IF($B$47=0,0,N28/$B$47) -> 0.032574167
A29: VIP | B29: Gamepass | C29: No | D29: 499 | E29: Day 7 | F29: =$B$5*INDEX($B$12:$B$15,MATCH(E29,$A$12:$A$15,0)) -> 80 | G29: 0.02 | H29: =G29*IF(C29="Yes",1-Inputs!$B$12*(1-Inputs!$B$13),1) -> 0.02 | I29: 1 | J29: =F29/$B$5*H29 -> 0.0016 | K29: =F29*H29 -> 1.6 | L29: =K29*I29*D29 -> 798.4 | M29: =L29*Inputs!$B$6 -> 558.88 | N29: =M29*Inputs!$B$5 -> 2.123744 | O29: =IF($B$47=0,0,N29/$B$47) -> 0.027181454
... A34: Cosmetics (outfits, skins, emotes) | B34: Developer product | C34: No | D34: 149 | E34: Day 7 | F34: =$B$5*INDEX($B$12:$B$15,MATCH(E34,$A$12:$A$15,0)) -> 80 | G34: 0.05 | H34: =G34*IF(C34="Yes",1-Inputs!$B$12*(1-Inputs!$B$13),1) -> 0.05 | I34: 2 | J34: =F34/$B$5*H34 -> 0.004 | K34: =F34*H34 -> 4 | L34: =K34*I34*D34 -> 1192 | M34: =L34*Inputs!$B$6 -> 834.4 | N34: =M34*Inputs!$B$5 -> 3.17072 | O34: =IF($B$47=0,0,N34/$B$47) -> 0.04058153
A35: Total (Robux products) | L35: =SUM(L18:L34) -> 27872.217 | M35: =SUM(M18:M34) -> 19510.552 | N35: =SUM(N18:N34) -> 74.140097 | O35: =SUM(O18:O34) -> 0.94890704
A37: Fan Club subscription (priced in real money)
A38: Price per month (USD) | B38: 4.99
A39: Offered to | B39: Day 7
A40: Chance one of them subscribes | B40: 0.02
A41: Months paid in the first 30 days | B41: 1
A42: Your share after app store and Roblox fees | B42: 0.5 | C42: Placeholder. Roblox's Earn on Roblox page gives no subscription share; check Creator Hub.
A43: Subscribers in the cohort | B43: =$B$5*INDEX($B$12:$B$15,MATCH(B39,$A$12:$A$15,0))*B40 -> 1.6
A44: Your cash from subscriptions (USD) | B44: =B43*B41*B38*B42 -> 3.992
A46: Results
A47: Your total revenue from this cohort (USD) | B47: =N35+B44 -> 78.132097
A48: Revenue per new player, first 30 days (USD) | B48: =B47/B5 -> 0.078132097
A49: Revenue per player still playing on day 7 (USD) | B49: =IF(B7=0,0,B47/(B5*B7)) -> 0.97665121
A50: What players spent, in real money (USD) | B50: =L35*Inputs!$B$7+B43*B41*B38 -> 356.38671 | C50: Includes the share Roblox, app stores and DevEx keep.
A51: Of every $1 players spend, you keep | B51: =IF(B50=0,0,B47/B50) -> 0.21923404
A52: Chance a new player pays anything (upper bound) | B52: =1-EXP(SUMPRODUCT(LN(1-J18:J34)))*(1-B43/B5) -> 0.082600074 | C52: Assumes purchases are independent. The real payer share is lower because the same players buy several things.
A53: Subscription share of revenue | B53: =IF(B47=0,0,B44/B47) -> 0.051092959
A55: Monthly projection (simple)
A56: New players per day | B56: 1000
A57: Monthly revenue (USD) | B57: =B56*30*B48 -> 2343.9629 | C57: Counts only each player's first 30 days. The Growth tab models older players, friends, comebacks and Creator Rewards.
A58: Monthly revenue target (USD) | B58: 1000
A59: New players per day needed to hit it | B59: =IF(B48=0,"-",ROUNDUP(B58/(30*B48),0)) -> 427
A61: Revenue per 1,000 new players (USD): day 1 retention vs. purchase odds
A62: Day 1 retention (down) / purchase odds x (across) | B62: 0.5 | C62: 0.75 | D62: 1 | E62: 1.5 | F62: 2
A63: 0.15 | B63: =B$62*($B$71+($A63/$B$6)*$B$72)/$B$5*1000 -> 24.229649 | C63: =C$62*($B$71+($A63/$B$6)*$B$72)/$B$5*1000 -> 36.344473 | D63: =D$62*($B$71+($A63/$B$6)*$B$72)/$B$5*1000 -> 48.459298 | E63: =E$62*($B$71+($A63/$B$6)*$B$72)/$B$5*1000 -> 72.688947 | F63: =F$62*($B$71+($A63/$B$6)*$B$72)/$B$5*1000 -> 96.918596
A64: 0.2 | B64: =B$62*($B$71+($A64/$B$6)*$B$72)/$B$5*1000 -> 31.647849 | C64: =C$62*($B$71+($A64/$B$6)*$B$72)/$B$5*1000 -> 47.471773 | D64: =D$62*($B$71+($A64/$B$6)*$B$72)/$B$5*1000 -> 63.295697 | E64: =E$62*($B$71+($A64/$B$6)*$B$72)/$B$5*1000 -> 94.943546 | F64: =F$62*($B$71+($A64/$B$6)*$B$72)/$B$5*1000 -> 126.59139
A65: 0.25 | B65: =B$62*($B$71+($A65/$B$6)*$B$72)/$B$5*1000 -> 39.066048 | C65: =C$62*($B$71+($A65/$B$6)*$B$72)/$B$5*1000 -> 58.599072 | D65: =D$62*($B$71+($A65/$B$6)*$B$72)/$B$5*1000 -> 78.132097 | E65: =E$62*($B$71+($A65/$B$6)*$B$72)/$B$5*1000 -> 117.19814 | F65: =F$62*($B$71+($A65/$B$6)*$B$72)/$B$5*1000 -> 156.26419
A66: 0.3 | B66: =B$62*($B$71+($A66/$B$6)*$B$72)/$B$5*1000 -> 46.484248 | C66: =C$62*($B$71+($A66/$B$6)*$B$72)/$B$5*1000 -> 69.726372 | D66: =D$62*($B$71+($A66/$B$6)*$B$72)/$B$5*1000 -> 92.968496 | E66: =E$62*($B$71+($A66/$B$6)*$B$72)/$B$5*1000 -> 139.45274 | F66: =F$62*($B$71+($A66/$B$6)*$B$72)/$B$5*1000 -> 185.93699
A67: 0.35 | B67: =B$62*($B$71+($A67/$B$6)*$B$72)/$B$5*1000 -> 53.902448 | C67: =C$62*($B$71+($A67/$B$6)*$B$72)/$B$5*1000 -> 80.853671 | D67: =D$62*($B$71+($A67/$B$6)*$B$72)/$B$5*1000 -> 107.8049 | E67: =E$62*($B$71+($A67/$B$6)*$B$72)/$B$5*1000 -> 161.70734 | F67: =F$62*($B$71+($A67/$B$6)*$B$72)/$B$5*1000 -> 215.60979
A68: Assumes day 7 and day 30 retention rise and fall in proportion to day 1.
A70: Helper for the grid
A71: Revenue from first-session offers (USD) | B71: =SUMIFS($N$18:$N$34,$E$18:$E$34,"New") -> 3.9501
A72: Revenue from players who come back (USD) | B72: =B47-B71 -> 74.181997

Sheet Growth
A1: Growth: where players come from, who stays, what they are worth
A2: Weekly model of the first 26 weeks. Yellow cells are placeholders: replace them with Creator Analytics numbers.
A4: Where new players come from
A5: Organic new players in week 1 (Roblox recommendations and search) | B5: 1500
A6: Organic growth per week | B6: 0.03 | C6: Roblox recommendations reward 28-day retention, play days, co-play and spend days (DevForum, June 2026).
A7: New players from friend invites per week, per 100 average daily players | B7: 5 | C7: Friend bonuses (luck per friend, gifting, co-op events) push this up.
A8: New players per week from off-Roblox content (TikTok, YouTube links) | B8: 300 | C8: Direct links to your game page also earn Audience Expansion Rewards (below).
A9: Paid ads budget per week (USD) | B9: 0
A10: Cost per new player from ads (USD) | B10: 0.3 | C10: Placeholder. Check your cost in Roblox Ads Manager.
A11: A comeback starts every (weeks) | B11: =MAX(1,ROUND(Inputs!$B$10/7,0)) -> 3 | C11: From the comeback length on Inputs.
A12: New players in a comeback week (x normal) | B12: 1.5
A13: Lapsed players who come back in a comeback week | B13: 0.05
A14: Days a returning player plays during that week | B14: 3
A16: Retention (from the Revenue tab)
A17: Still playing on day 1 | B17: =Revenue!$B$6 -> 0.25
A18: Still playing on day 7 | B18: =Revenue!$B$7 -> 0.08
A19: Still playing on day 30 | B19: =Revenue!$B$8 -> 0.03
A20: Curve steepness, days 1-7 (fitted) | B20: =LN(B18/B17)/LN(7) -> -0.58555339
A21: Curve steepness after day 7 (fitted) | B21: =LN(B19/B18)/LN(30/7) -> -0.6739764 | C21: Retention follows a power curve through day 1, day 7 and day 30, then keeps the same slope after day 30.
A22: Player-days in a new player's first 30 days | B22: =7*SUM(B44:B47)+2*B48 -> 2.8950392
A24: Money
A25: 30-day revenue per new player (Revenue tab) | B25: =Revenue!$B$48 -> 0.078132097
A26: Revenue per daily player per day (fitted) | B26: =B25/B22 -> 0.026988269 | C26: Spread so the first 30 days match the Revenue tab.
A27: Spending after the first month (x first-month rate) | B27: 1 | C27: Players who stay often spend more; raise this once you see real data.
A28: Share of your players who are Roblox 'Active Spenders' | B28: 0.1 | C28: Spent $9.99+ on Roblox in the last 60 days (Creator Rewards definition).
A29: Share of their play days that qualify | B29: 0.6 | C29: 10+ minutes in your game that day, and yours is among the first 3 games they launch.
A30: Robux per qualifying Active Spender day | B30: 5 | C30: Creator Rewards, Daily Engagement Rewards (DevForum, July 2025). May change.
A31: Off-Roblox new players who are new to Roblox, or back after 60+ days | B31: 0.1 | C31: Counts only if they arrive by a direct link or search your game by name, then play 10+ minutes.
A32: Their Robux purchases in their first two months (USD, counted up to $100) | B32: 3 | C32: Average including the many who buy nothing.
A33: Audience Expansion revenue share | B33: 0.35 | C33: Creator Rewards, Audience Expansion Rewards. Paid after a 60-day hold.
A34: Creator Rewards per daily player per day (USD) | B34: =B28*B29*B30*Inputs!$B$5 -> 0.00114
A36: Results
A37: Average daily players in week 26 | B37: =I98 -> 2547.3155
A38: Revenue over 26 weeks (USD, purchases + Creator Rewards) | B38: =J99+K99 -> 10394.528
A39: Value of one new player over 26 weeks (USD) | B39: =B26*7*(SUM(B44:B48)+B27*SUM(B49:B69))+B34*7*SUM(B44:B69) -> 0.14390095
A40: Do ads pay back within 26 weeks? | B40: =IF(B10<=0,"-",IF(B39>=B10,"OK: an ad player earns back their cost","No: an ad player costs more than they earn")) -> No: an ad player costs more than they earn
A41: Revenue from Creator Rewards (share of total) | B41: =IF(B38=0,0,K99/B38) -> 0.12775725
A43: Weeks since install | B43: Share playing on a typical day that week
A44: 0 | B44: =(1+$B$17*(1^$B$20+2^$B$20+3^$B$20+4^$B$20+5^$B$20+6^$B$20))/7 -> 0.26342665 | C44: Install week: day 0 plus days 1-6 averaged.
A45: 1 | B45: =$B$18*((7*A45+3)/7)^$B$21 -> 0.06290566
A46: 2 | B46: =$B$18*((7*A46+3)/7)^$B$21 -> 0.043991887
A47: 3 | B47: =$B$18*((7*A47+3)/7)^$B$21 -> 0.034868745
A48: 4 | B48: =$B$18*((7*A48+3)/7)^$B$21 -> 0.029344285
A49: 5 | B49: =$B$18*((7*A49+3)/7)^$B$21 -> 0.025581692
A50: 6 | B50: =$B$18*((7*A50+3)/7)^$B$21 -> 0.02282653
A51: 7 | B51: =$B$18*((7*A51+3)/7)^$B$21 -> 0.020707152
A52: 8 | B52: =$B$18*((7*A52+3)/7)^$B$21 -> 0.01901751
A53: 9 | B53: =$B$18*((7*A53+3)/7)^$B$21 -> 0.017633416
A54: 10 | B54: =$B$18*((7*A54+3)/7)^$B$21 -> 0.016475192
A55: 11 | B55: =$B$18*((7*A55+3)/7)^$B$21 -> 0.015489178
A56: 12 | B56: =$B$18*((7*A56+3)/7)^$B$21 -> 0.014637804
... A69: 25 | B69: =$B$18*((7*A69+3)/7)^$B$21 -> 0.0090351662
A71: Week by week
A72: Week | B72: Comeback week? | C72: Organic | D72: Friend invites | E72: Off-Roblox content | F72: Paid ads | G72: New players | H72: Returning players | I72: Average daily players | J72: Purchase revenue (USD) | K72: Creator Rewards (USD) | L72: Ad spend (USD) | M72: Net (USD) | N72: Cumulative net (USD)
A73: 1 | B73: =IF(AND(A73>1,MOD(A73-1,$B$11)=0),"Yes","") | C73: =$B$5*(1+$B$6)^(A73-1)*IF(B73="Yes",$B$12,1) -> 1500 | D73: 0 | E73: =$B$8*IF(B73="Yes",$B$12,1) -> 300 | F73: =IF($B$10<=0,0,$B$9/$B$10) -> 0 | G73: =SUM(C73:F73) -> 1800 | H73: 0 | I73: =SUM(C$103:C$128)+H73*$B$14/7 -> 474.16798 | J73: =$B$26*7*SUMPRODUCT(C$103:C$128,1+($B$27-1)*((A73-$A$103:$A$128)>=5))+H73*$B$14*$B$26 -> 89.578811 | K73: =I73*7*$B$34+E73*$B$31*MIN($B$32,100)*$B$33 -> 35.28386 | L73: =$B$9 -> 0 | M73: =J73+K73-L73 -> 124.86267 | N73: =M73 -> 124.86267
A74: 2 | B74: =IF(AND(A74>1,MOD(A74-1,$B$11)=0),"Yes","") | C74: =$B$5*(1+$B$6)^(A74-1)*IF(B74="Yes",$B$12,1) -> 1545 | D74: =I73/100*$B$7 -> 23.708399 | E74: =$B$8*IF(B74="Yes",$B$12,1) -> 300 | F74: =IF($B$10<=0,0,$B$9/$B$10) -> 0 | G74: =SUM(C74:F74) -> 1868.7084 | H74: =IF(B74="Yes",MAX(0,SUM(G$73:G73)-I73)*$B$13,0) -> 0 | I74: =SUM(D$103:D$128)+H74*$B$14/7 -> 605.49779 | J74: =$B$26*7*SUMPRODUCT(D$103:D$128,1+($B$27-1)*((A74-$A$103:$A$128)>=5))+H74*$B$14*$B$26 -> 114.38936 | K74: =I74*7*$B$34+E74*$B$31*MIN($B$32,100)*$B$33 -> 36.331872 | L74: =$B$9 -> 0 | M74: =J74+K74-L74 -> 150.72123 | N74: =N73+M74 -> 275.5839
A75: 3 | B75: =IF(AND(A75>1,MOD(A75-1,$B$11)=0),"Yes","") | C75: =$B$5*(1+$B$6)^(A75-1)*IF(B75="Yes",$B$12,1) -> 1591.35 | D75: =I74/100*$B$7 -> 30.274889 | E75: =$B$8*IF(B75="Yes",$B$12,1) -> 300 | F75: =IF($B$10<=0,0,$B$9/$B$10) -> 0 | G75: =SUM(C75:F75) -> 1921.6249 | H75: =IF(B75="Yes",MAX(0,SUM(G$73:G74)-I74)*$B$13,0) -> 0 | I75: =SUM(E$103:E$128)+H75*$B$14/7 -> 702.94495 | J75: =$B$26*7*SUMPRODUCT(E$103:E$128,1+($B$27-1)*((A75-$A$103:$A$128)>=5))+H75*$B$14*$B$26 -> 132.79887 | K75: =I75*7*$B$34+E75*$B$31*MIN($B$32,100)*$B$33 -> 37.109501 | L75: =$B$9 -> 0 | M75: =J75+K75-L75 -> 169.90837 | N75: =N74+M75 -> 445.49228
A76: 4 | B76: =IF(AND(A76>1,MOD(A76-1,$B$11)=0),"Yes","") -> Yes | C76: =$B$5*(1+$B$6)^(A76-1)*IF(B76="Yes",$B$12,1) -> 2458.6357 | D76: =I75/100*$B$7 -> 35.147247 | E76: =$B$8*IF(B76="Yes",$B$12,1) -> 450 | F76: =IF($B$10<=0,0,$B$9/$B$10) -> 0 | G76: =SUM(C76:F76) -> 2943.783 | H76: =IF(B76="Yes",MAX(0,SUM(G$73:G75)-I75)*$B$13,0) -> 244.36942 | I76: =SUM(F$103:F$128)+H76*$B$14/7 -> 1146.0535 | J76: =$B$26*7*SUMPRODUCT(F$103:F$128,1+($B$27-1)*((A76-$A$103:$A$128)>=5))+H76*$B$14*$B$26 -> 216.51 | K76: =I76*7*$B$34+E76*$B$31*MIN($B$32,100)*$B$33 -> 56.395507 | L76: =$B$9 -> 0 | M76: =J76+K76-L76 -> 272.90551 | N76: =N75+M76 -> 718.39778
A77: 5 | B77: =IF(AND(A77>1,MOD(A77-1,$B$11)=0),"Yes","") | C77: =$B$5*(1+$B$6)^(A77-1)*IF(B77="Yes",$B$12,1) -> 1688.2632 | D77: =I76/100*$B$7 -> 57.302674 | E77: =$B$8*IF(B77="Yes",$B$12,1) -> 300 | F77: =IF($B$10<=0,0,$B$9/$B$10) -> 0 | G77: =SUM(C77:F77) -> 2045.5659 | H77: =IF(B77="Yes",MAX(0,SUM(G$73:G76)-I76)*$B$13,0) -> 0 | I77: =SUM(G$103:G$128)+H77*$B$14/7 -> 926.55232 | J77: =$B$26*7*SUMPRODUCT(G$103:G$128,1+($B$27-1)*((A77-$A$103:$A$128)>=5))+H77*$B$14*$B$26 -> 175.0423 | K77: =I77*7*$B$34+E77*$B$31*MIN($B$32,100)*$B$33 -> 38.893888 | L77: =$B$9 -> 0 | M77: =J77+K77-L77 -> 213.93619 | N77: =N76+M77 -> 932.33397
A78: 6 | B78: =IF(AND(A78>1,MOD(A78-1,$B$11)=0),"Yes","") | C78: =$B$5*(1+$B$6)^(A78-1)*IF(B78="Yes",$B$12,1) -> 1738.9111 | D78: =I77/100*$B$7 -> 46.327616 | E78: =$B$8*IF(B78="Yes",$B$12,1) -> 300 | F78: =IF($B$10<=0,0,$B$9/$B$10) -> 0 | G78: =SUM(C78:F78) -> 2085.2387 | H78: =IF(B78="Yes",MAX(0,SUM(G$73:G77)-I77)*$B$13,0) -> 0 | I78: =SUM(H$103:H$128)+H78*$B$14/7 -> 975.37531 | J78: =$B$26*7*SUMPRODUCT(H$103:H$128,1+($B$27-1)*((A78-$A$103:$A$128)>=5))+H78*$B$14*$B$26 -> 184.26584 | K78: =I78*7*$B$34+E78*$B$31*MIN($B$32,100)*$B$33 -> 39.283495 | L78: =$B$9 -> 0 | M78: =J78+K78-L78 -> 223.54933 | N78: =N77+M78 -> 1155.8833
A79: 7 | B79: =IF(AND(A79>1,MOD(A79-1,$B$11)=0),"Yes","") -> Yes | C79: =$B$5*(1+$B$6)^(A79-1)*IF(B79="Yes",$B$12,1) -> 2686.6177 | D79: =I78/100*$B$7 -> 48.768765 | E79: =$B$8*IF(B79="Yes",$B$12,1) -> 450 | F79: =IF($B$10<=0,0,$B$9/$B$10) -> 0 | G79: =SUM(C79:F79) -> 3185.3864 | H79: =IF(B79="Yes",MAX(0,SUM(G$73:G78)-I78)*$B$13,0) -> 584.47728 | I79: =SUM(I$103:I$128)+H79*$B$14/7 -> 1558.6948 | J79: =$B$26*7*SUMPRODUCT(I$103:I$128,1+($B$27-1)*((A79-$A$103:$A$128)>=5))+H79*$B$14*$B$26 -> 294.46532 | K79: =I79*7*$B$34+E79*$B$31*MIN($B$32,100)*$B$33 -> 59.688384 | L79: =$B$9 -> 0 | M79: =J79+K79-L79 -> 354.1537 | N79: =N78+M79 -> 1510.037
A80: 8 | B80: =IF(AND(A80>1,MOD(A80-1,$B$11)=0),"Yes","") | C80: =$B$5*(1+$B$6)^(A80-1)*IF(B80="Yes",$B$12,1) -> 1844.8108 | D80: =I79/100*$B$7 -> 77.934739 | E80: =$B$8*IF(B80="Yes",$B$12,1) -> 300 | F80: =IF($B$10<=0,0,$B$9/$B$10) -> 0 | G80: =SUM(C80:F80) -> 2222.7455 | H80: =IF(B80="Yes",MAX(0,SUM(G$73:G79)-I79)*$B$13,0) -> 0 | I80: =SUM(J$103:J$128)+H80*$B$14/7 -> 1164.4398 | J80: =$B$26*7*SUMPRODUCT(J$103:J$128,1+($B$27-1)*((A80-$A$103:$A$128)>=5))+H80*$B$14*$B$26 -> 219.9835 | K80: =I80*7*$B$34+E80*$B$31*MIN($B$32,100)*$B$33 -> 40.792229 | L80: =$B$9 -> 0 | M80: =J80+K80-L80 -> 260.77573 | N80: =N79+M80 -> 1770.8127
A81: 9 | B81: =IF(AND(A81>1,MOD(A81-1,$B$11)=0),"Yes","") | C81: =$B$5*(1+$B$6)^(A81-1)*IF(B81="Yes",$B$12,1) -> 1900.1551 | D81: =I80/100*$B$7 -> 58.221989 | E81: =$B$8*IF(B81="Yes",$B$12,1) -> 300 | F81: =IF($B$10<=0,0,$B$9/$B$10) -> 0 | G81: =SUM(C81:F81) -> 2258.3771 | H81: =IF(B81="Yes",MAX(0,SUM(G$73:G80)-I80)*$B$13,0) -> 0 | I81: =SUM(K$103:K$128)+H81*$B$14/7 -> 1199.7046 | J81: =$B$26*7*SUMPRODUCT(K$103:K$128,1+($B$27-1)*((A81-$A$103:$A$128)>=5))+H81*$B$14*$B$26 -> 226.64566 | K81: =I81*7*$B$34+E81*$B$31*MIN($B$32,100)*$B$33 -> 41.073643 | L81: =$B$9 -> 0 | M81: =J81+K81-L81 -> 267.7193 | N81: =N80+M81 -> 2038.532
A82: 10 | B82: =IF(AND(A82>1,MOD(A82-1,$B$11)=0),"Yes","") -> Yes | C82: =$B$5*(1+$B$6)^(A82-1)*IF(B82="Yes",$B$12,1) -> 2935.7397 | D82: =I81/100*$B$7 -> 59.98523 | E82: =$B$8*IF(B82="Yes",$B$12,1) -> 450 | F82: =IF($B$10<=0,0,$B$9/$B$10) -> 0 | G82: =SUM(C82:F82) -> 3445.7249 | H82: =IF(B82="Yes",MAX(0,SUM(G$73:G81)-I81)*$B$13,0) -> 956.58627 | I82: =SUM(L$103:L$128)+H82*$B$14/7 -> 1956.3642 | J82: =$B$26*7*SUMPRODUCT(L$103:L$128,1+($B$27-1)*((A82-$A$103:$A$128)>=5))+H82*$B$14*$B$26 -> 369.59218 | K82: =I82*7*$B$34+E82*$B$31*MIN($B$32,100)*$B$33 -> 62.861786 | L82: =$B$9 -> 0 | M82: =J82+K82-L82 -> 432.45396 | N82: =N81+M82 -> 2470.986
A83: 11 | B83: =IF(AND(A83>1,MOD(A83-1,$B$11)=0),"Yes","") | C83: =$B$5*(1+$B$6)^(A83-1)*IF(B83="Yes",$B$12,1) -> 2015.8746 | D83: =I82/100*$B$7 -> 97.818208 | E83: =$B$8*IF(B83="Yes",$B$12,1) -> 300 | F83: =IF($B$10<=0,0,$B$9/$B$10) -> 0 | G83: =SUM(C83:F83) -> 2413.6928 | H83: =IF(B83="Yes",MAX(0,SUM(G$73:G82)-I82)*$B$13,0) -> 0 | I83: =SUM(M$103:M$128)+H83*$B$14/7 -> 1383.0602 | J83: =$B$26*7*SUMPRODUCT(M$103:M$128,1+($B$27-1)*((A83-$A$103:$A$128)>=5))+H83*$B$14*$B$26 -> 261.2848 | K83: =I83*7*$B$34+E83*$B$31*MIN($B$32,100)*$B$33 -> 42.53682 | L83: =$B$9 -> 0 | M83: =J83+K83-L83 -> 303.82162 | N83: =N82+M83 -> 2774.8076
A84: 12 | B84: =IF(AND(A84>1,MOD(A84-1,$B$11)=0),"Yes","") | C84: =$B$5*(1+$B$6)^(A84-1)*IF(B84="Yes",$B$12,1) -> 2076.3508 | D84: =I83/100*$B$7 -> 69.153008 | E84: =$B$8*IF(B84="Yes",$B$12,1) -> 300 | F84: =IF($B$10<=0,0,$B$9/$B$10) -> 0 | G84: =SUM(C84:F84) -> 2445.5038 | H84: =IF(B84="Yes",MAX(0,SUM(G$73:G83)-I83)*$B$13,0) -> 0 | I84: =SUM(N$103:N$128)+H84*$B$14/7 -> 1411.5817 | J84: =$B$26*7*SUMPRODUCT(N$103:N$128,1+($B$27-1)*((A84-$A$103:$A$128)>=5))+H84*$B$14*$B$26 -> 266.67302 | K84: =I84*7*$B$34+E84*$B$31*MIN($B$32,100)*$B$33 -> 42.764422 | L84: =$B$9 -> 0 | M84: =J84+K84-L84 -> 309.43745 | N84: =N83+M84 -> 3084.2451
A85: 13 | B85: =IF(AND(A85>1,MOD(A85-1,$B$11)=0),"Yes","") -> Yes | C85: =$B$5*(1+$B$6)^(A85-1)*IF(B85="Yes",$B$12,1) -> 3207.962 | D85: =I84/100*$B$7 -> 70.579084 | E85: =$B$8*IF(B85="Yes",$B$12,1) -> 450 | F85: =IF($B$10<=0,0,$B$9/$B$10) -> 0 | G85: =SUM(C85:F85) -> 3728.5411 | H85: =IF(B85="Yes",MAX(0,SUM(G$73:G84)-I84)*$B$13,0) -> 1361.2385 | I85: =SUM(O$103:O$128)+H85*$B$14/7 -> 2362.5372 | J85: =$B$26*7*SUMPRODUCT(O$103:O$128,1+($B$27-1)*((A85-$A$103:$A$128)>=5))+H85*$B$14*$B$26 -> 446.32554 | K85: =I85*7*$B$34+E85*$B$31*MIN($B$32,100)*$B$33 -> 66.103047 | L85: =$B$9 -> 0 | M85: =J85+K85-L85 -> 512.42858 | N85: =N84+M85 -> 3596.6736
A86: 14 | B86: =IF(AND(A86>1,MOD(A86-1,$B$11)=0),"Yes","") | C86: =$B$5*(1+$B$6)^(A86-1)*IF(B86="Yes",$B$12,1) -> 2202.8006 | D86: =I85/100*$B$7 -> 118.12686 | E86: =$B$8*IF(B86="Yes",$B$12,1) -> 300 | F86: =IF($B$10<=0,0,$B$9/$B$10) -> 0 | G86: =SUM(C86:F86) -> 2620.9274 | H86: =IF(B86="Yes",MAX(0,SUM(G$73:G85)-I85)*$B$13,0) -> 0 | I86: =SUM(P$103:P$128)+H86*$B$14/7 -> 1598.6495 | J86: =$B$26*7*SUMPRODUCT(P$103:P$128,1+($B$27-1)*((A86-$A$103:$A$128)>=5))+H86*$B$14*$B$26 -> 302.01348 | K86: =I86*7*$B$34+E86*$B$31*MIN($B$32,100)*$B$33 -> 44.257223 | L86: =$B$9 -> 0 | M86: =J86+K86-L86 -> 346.2707 | N86: =N85+M86 -> 3942.9443
A87: 15 | B87: =IF(AND(A87>1,MOD(A87-1,$B$11)=0),"Yes","") | C87: =$B$5*(1+$B$6)^(A87-1)*IF(B87="Yes",$B$12,1) -> 2268.8846 | D87: =I86/100*$B$7 -> 79.932475 | E87: =$B$8*IF(B87="Yes",$B$12,1) -> 300 | F87: =IF($B$10<=0,0,$B$9/$B$10) -> 0 | G87: =SUM(C87:F87) -> 2648.8171 | H87: =IF(B87="Yes",MAX(0,SUM(G$73:G86)-I86)*$B$13,0) -> 0 | I87: =SUM(Q$103:Q$128)+H87*$B$14/7 -> 1623.0557 | J87: =$B$26*7*SUMPRODUCT(Q$103:Q$128,1+($B$27-1)*((A87-$A$103:$A$128)>=5))+H87*$B$14*$B$26 -> 306.62425 | K87: =I87*7*$B$34+E87*$B$31*MIN($B$32,100)*$B$33 -> 44.451985 | L87: =$B$9 -> 0 | M87: =J87+K87-L87 -> 351.07624 | N87: =N86+M87 -> 4294.0206
A88: 16 | B88: =IF(AND(A88>1,MOD(A88-1,$B$11)=0),"Yes","") -> Yes | C88: =$B$5*(1+$B$6)^(A88-1)*IF(B88="Yes",$B$12,1) -> 3505.4267 | D88: =I87/100*$B$7 -> 81.152786 | E88: =$B$8*IF(B88="Yes",$B$12,1) -> 450 | F88: =IF($B$10<=0,0,$B$9/$B$10) -> 0 | G88: =SUM(C88:F88) -> 4036.5795 | H88: =IF(B88="Yes",MAX(0,SUM(G$73:G87)-I87)*$B$13,0) -> 1800.5791 | I88: =SUM(R$103:R$128)+H88*$B$14/7 -> 2787.6608 | J88: =$B$26*7*SUMPRODUCT(R$103:R$128,1+($B$27-1)*((A88-$A$103:$A$128)>=5))+H88*$B$14*$B$26 -> 526.63898 | K88: =I88*7*$B$34+E88*$B$31*MIN($B$32,100)*$B$33 -> 69.495533 | L88: =$B$9 -> 0 | M88: =J88+K88-L88 -> 596.13451 | N88: =N87+M88 -> 4890.1551
A89: 17 | B89: =IF(AND(A89>1,MOD(A89-1,$B$11)=0),"Yes","") | C89: =$B$5*(1+$B$6)^(A89-1)*IF(B89="Yes",$B$12,1) -> 2407.0597 | D89: =I88/100*$B$7 -> 139.38304 | E89: =$B$8*IF(B89="Yes",$B$12,1) -> 300 | F89: =IF($B$10<=0,0,$B$9/$B$10) -> 0 | G89: =SUM(C89:F89) -> 2846.4427 | H89: =IF(B89="Yes",MAX(0,SUM(G$73:G88)-I88)*$B$13,0) -> 0 | I89: =SUM(S$103:S$128)+H89*$B$14/7 -> 1818.7642 | J89: =$B$26*7*SUMPRODUCT(S$103:S$128,1+($B$27-1)*((A89-$A$103:$A$128)>=5))+H89*$B$14*$B$26 -> 343.59708 | K89: =I89*7*$B$34+E89*$B$31*MIN($B$32,100)*$B$33 -> 46.013738 | L89: =$B$9 -> 0 | M89: =J89+K89-L89 -> 389.61081 | N89: =N88+M89 -> 5279.7659
A90: 18 | B90: =IF(AND(A90>1,MOD(A90-1,$B$11)=0),"Yes","") | C90: =$B$5*(1+$B$6)^(A90-1)*IF(B90="Yes",$B$12,1) -> 2479.2714 | D90: =I89/100*$B$7 -> 90.938208 | E90: =$B$8*IF(B90="Yes",$B$12,1) -> 300 | F90: =IF($B$10<=0,0,$B$9/$B$10) -> 0 | G90: =SUM(C90:F90) -> 2870.2097 | H90: =IF(B90="Yes",MAX(0,SUM(G$73:G89)-I89)*$B$13,0) -> 0 | I90: =SUM(T$103:T$128)+H90*$B$14/7 -> 1840.36 | J90: =$B$26*7*SUMPRODUCT(T$103:T$128,1+($B$27-1)*((A90-$A$103:$A$128)>=5))+H90*$B$14*$B$26 -> 347.67691 | K90: =I90*7*$B$34+E90*$B$31*MIN($B$32,100)*$B$33 -> 46.186073 | L90: =$B$9 -> 0 | M90: =J90+K90-L90 -> 393.86299 | N90: =N89+M90 -> 5673.6289
A91: 19 | B91: =IF(AND(A91>1,MOD(A91-1,$B$11)=0),"Yes","") -> Yes | C91: =$B$5*(1+$B$6)^(A91-1)*IF(B91="Yes",$B$12,1) -> 3830.4744 | D91: =I90/100*$B$7 -> 92.017999 | E91: =$B$8*IF(B91="Yes",$B$12,1) -> 450 | F91: =IF($B$10<=0,0,$B$9/$B$10) -> 0 | G91: =SUM(C91:F91) -> 4372.4924 | H91: =IF(B91="Yes",MAX(0,SUM(G$73:G90)-I90)*$B$13,0) -> 2277.3754 | I91: =SUM(U$103:U$128)+H91*$B$14/7 -> 3238.4095 | J91: =$B$26*7*SUMPRODUCT(U$103:U$128,1+($B$27-1)*((A91-$A$103:$A$128)>=5))+H91*$B$14*$B$26 -> 611.79347 | K91: =I91*7*$B$34+E91*$B$31*MIN($B$32,100)*$B$33 -> 73.092508 | L91: =$B$9 -> 0 | M91: =J91+K91-L91 -> 684.88598 | N91: =N90+M91 -> 6358.5149
A92: 20 | B92: =IF(AND(A92>1,MOD(A92-1,$B$11)=0),"Yes","") | C92: =$B$5*(1+$B$6)^(A92-1)*IF(B92="Yes",$B$12,1) -> 2630.2591 | D92: =I91/100*$B$7 -> 161.92048 | E92: =$B$8*IF(B92="Yes",$B$12,1) -> 300 | F92: =IF($B$10<=0,0,$B$9/$B$10) -> 0 | G92: =SUM(C92:F92) -> 3092.1796 | H92: =IF(B92="Yes",MAX(0,SUM(G$73:G91)-I91)*$B$13,0) -> 0 | I92: =SUM(V$103:V$128)+H92*$B$14/7 -> 2048.0513 | J92: =$B$26*7*SUMPRODUCT(V$103:V$128,1+($B$27-1)*((A92-$A$103:$A$128)>=5))+H92*$B$14*$B$26 -> 386.91352 | K92: =I92*7*$B$34+E92*$B$31*MIN($B$32,100)*$B$33 -> 47.84345 | L92: =$B$9 -> 0 | M92: =J92+K92-L92 -> 434.75697 | N92: =N91+M92 -> 6793.2718
A93: 21 | B93: =IF(AND(A93>1,MOD(A93-1,$B$11)=0),"Yes","") | C93: =$B$5*(1+$B$6)^(A93-1)*IF(B93="Yes",$B$12,1) -> 2709.1669 | D93: =I92/100*$B$7 -> 102.40257 | E93: =$B$8*IF(B93="Yes",$B$12,1) -> 300 | F93: =IF($B$10<=0,0,$B$9/$B$10) -> 0 | G93: =SUM(C93:F93) -> 3111.5694 | H93: =IF(B93="Yes",MAX(0,SUM(G$73:G92)-I92)*$B$13,0) -> 0 | I93: =SUM(W$103:W$128)+H93*$B$14/7 -> 2067.5835 | J93: =$B$26*7*SUMPRODUCT(W$103:W$128,1+($B$27-1)*((A93-$A$103:$A$128)>=5))+H93*$B$14*$B$26 -> 390.60349 | K93: =I93*7*$B$34+E93*$B$31*MIN($B$32,100)*$B$33 -> 47.999316 | L93: =$B$9 -> 0 | M93: =J93+K93-L93 -> 438.60281 | N93: =N92+M93 -> 7231.8747
A94: 22 | B94: =IF(AND(A94>1,MOD(A94-1,$B$11)=0),"Yes","") -> Yes | C94: =$B$5*(1+$B$6)^(A94-1)*IF(B94="Yes",$B$12,1) -> 4185.6628 | D94: =I93/100*$B$7 -> 103.37917 | E94: =$B$8*IF(B94="Yes",$B$12,1) -> 450 | F94: =IF($B$10<=0,0,$B$9/$B$10) -> 0 | G94: =SUM(C94:F94) -> 4739.042 | H94: =IF(B94="Yes",MAX(0,SUM(G$73:G93)-I93)*$B$13,0) -> 2794.8263 | I94: =SUM(X$103:X$128)+H94*$B$14/7 -> 3720.0538 | J94: =$B$26*7*SUMPRODUCT(X$103:X$128,1+($B$27-1)*((A94-$A$103:$A$128)>=5))+H94*$B$14*$B$26 -> 702.78469 | K94: =I94*7*$B$34+E94*$B$31*MIN($B$32,100)*$B$33 -> 76.936029 | L94: =$B$9 -> 0 | M94: =J94+K94-L94 -> 779.72072 | N94: =N93+M94 -> 8011.5954
A95: 23 | B95: =IF(AND(A95>1,MOD(A95-1,$B$11)=0),"Yes","") | C95: =$B$5*(1+$B$6)^(A95-1)*IF(B95="Yes",$B$12,1) -> 2874.1551 | D95: =I94/100*$B$7 -> 186.00269 | E95: =$B$8*IF(B95="Yes",$B$12,1) -> 300 | F95: =IF($B$10<=0,0,$B$9/$B$10) -> 0 | G95: =SUM(C95:F95) -> 3360.1578 | H95: =IF(B95="Yes",MAX(0,SUM(G$73:G94)-I94)*$B$13,0) -> 0 | I95: =SUM(Y$103:Y$128)+H95*$B$14/7 -> 2289.9424 | J95: =$B$26*7*SUMPRODUCT(Y$103:Y$128,1+($B$27-1)*((A95-$A$103:$A$128)>=5))+H95*$B$14*$B$26 -> 432.61106 | K95: =I95*7*$B$34+E95*$B$31*MIN($B$32,100)*$B$33 -> 49.77374 | L95: =$B$9 -> 0 | M95: =J95+K95-L95 -> 482.3848 | N95: =N94+M95 -> 8493.9802
A96: 24 | B96: =IF(AND(A96>1,MOD(A96-1,$B$11)=0),"Yes","") | C96: =$B$5*(1+$B$6)^(A96-1)*IF(B96="Yes",$B$12,1) -> 2960.3798 | D96: =I95/100*$B$7 -> 114.49712 | E96: =$B$8*IF(B96="Yes",$B$12,1) -> 300 | F96: =IF($B$10<=0,0,$B$9/$B$10) -> 0 | G96: =SUM(C96:F96) -> 3374.8769 | H96: =IF(B96="Yes",MAX(0,SUM(G$73:G95)-I95)*$B$13,0) -> 0 | I96: =SUM(Z$103:Z$128)+H96*$B$14/7 -> 2307.8795 | J96: =$B$26*7*SUMPRODUCT(Z$103:Z$128,1+($B$27-1)*((A96-$A$103:$A$128)>=5))+H96*$B$14*$B$26 -> 435.99972 | K96: =I96*7*$B$34+E96*$B$31*MIN($B$32,100)*$B$33 -> 49.916879 | L96: =$B$9 -> 0 | M96: =J96+K96-L96 -> 485.9166 | N96: =N95+M96 -> 8979.8968
A97: 25 | B97: =IF(AND(A97>1,MOD(A97-1,$B$11)=0),"Yes","") -> Yes | C97: =$B$5*(1+$B$6)^(A97-1)*IF(B97="Yes",$B$12,1) -> 4573.7867 | D97: =I96/100*$B$7 -> 115.39398 | E97: =$B$8*IF(B97="Yes",$B$12,1) -> 450 | F97: =IF($B$10<=0,0,$B$9/$B$10) -> 0 | G97: =SUM(C97:F97) -> 5139.1807 | H97: =IF(B97="Yes",MAX(0,SUM(G$73:G96)-I96)*$B$13,0) -> 3356.5154 | I97: =SUM(AA$103:AA$128)+H97*$B$14/7 -> 4237.3265 | J97: =$B$26*7*SUMPRODUCT(AA$103:AA$128,1+($B$27-1)*((A97-$A$103:$A$128)>=5))+H97*$B$14*$B$26 -> 800.50675 | K97: =I97*7*$B$34+E97*$B$31*MIN($B$32,100)*$B$33 -> 81.063865 | L97: =$B$9 -> 0 | M97: =J97+K97-L97 -> 881.57061 | N97: =N96+M97 -> 9861.4674
A98: 26 | B98: =IF(AND(A98>1,MOD(A98-1,$B$11)=0),"Yes","") | C98: =$B$5*(1+$B$6)^(A98-1)*IF(B98="Yes",$B$12,1) -> 3140.6669 | D98: =I97/100*$B$7 -> 211.86632 | E98: =$B$8*IF(B98="Yes",$B$12,1) -> 300 | F98: =IF($B$10<=0,0,$B$9/$B$10) -> 0 | G98: =SUM(C98:F98) -> 3652.5332 | H98: =IF(B98="Yes",MAX(0,SUM(G$73:G97)-I97)*$B$13,0) -> 0 | I98: =SUM(AB$103:AB$128)+H98*$B$14/7 -> 2547.3155 | J98: =$B$26*7*SUMPRODUCT(AB$103:AB$128,1+($B$27-1)*((A98-$A$103:$A$128)>=5))+H98*$B$14*$B$26 -> 481.23345 | K98: =I98*7*$B$34+E98*$B$31*MIN($B$32,100)*$B$33 -> 51.827578 | L98: =$B$9 -> 0 | M98: =J98+K98-L98 -> 533.06103 | N98: =N97+M98 -> 10394.528
A99: Total | C99: =SUM(C73:C98) -> 66957.665 | D99: =SUM(D73:D98) -> 2272.2355 | E99: =SUM(E73:E98) -> 9000 | F99: =SUM(F73:F98) -> 0 | G99: =SUM(G73:G98) -> 78229.901 | H99: =SUM(H73:H98) -> 13375.968 | J99: =SUM(J73:J98) -> 9066.552 | K99: =SUM(K73:K98) -> 1327.9764 | L99: =SUM(L73:L98) -> 0 | M99: =SUM(M73:M98) -> 10394.528
A101: Retention heat map: average daily players from each install week, by calendar week
A102: Install week | B102: New players | C102: Wk 1 | D102: Wk 2 | E102: Wk 3 | F102: Wk 4 | G102: Wk 5 | H102: Wk 6 | I102: Wk 7 | J102: Wk 8 | K102: Wk 9 | L102: Wk 10 | M102: Wk 11 | N102: Wk 12 | O102: Wk 13 | P102: Wk 14 | Q102: Wk 15 | R102: Wk 16 | S102: Wk 17 | T102: Wk 18 | U102: Wk 19 | V102: Wk 20 | W102: Wk 21 | X102: Wk 22 | Y102: Wk 23 | Z102: Wk 24 | AA102: Wk 25 | AB102: Wk 26
A103: 1 | B103: =G73 -> 1800 | C103: =$B103*$B$44 -> 474.16798 | D103: =$B103*$B$45 -> 113.23019 | E103: =$B103*$B$46 -> 79.185396 | F103: =$B103*$B$47 -> 62.763741 | G103: =$B103*$B$48 -> 52.819713 | H103: =$B103*$B$49 -> 46.047045 | I103: =$B103*$B$50 -> 41.087754 | J103: =$B103*$B$51 -> 37.272873 | K103: =$B103*$B$52 -> 34.231518 | L103: =$B103*$B$53 -> 31.740148 | M103: =$B103*$B$54 -> 29.655346 | N103: =$B103*$B$55 -> 27.880521 | O103: =$B103*$B$56 -> 26.348046 | P103: =$B103*$B$57 -> 25.00904 | Q103: =$B103*$B$58 -> 23.827217 | R103: =$B103*$B$59 -> 22.775032 | S103: =$B103*$B$60 -> 21.831165 | T103: =$B103*$B$61 -> 20.978834 | U103: =$B103*$B$62 -> 20.204633 | V103: =$B103*$B$63 -> 19.497716 | W103: =$B103*$B$64 -> 18.849203 | X103: =$B103*$B$65 -> 18.251748 | Y103: =$B103*$B$66 -> 17.699218 | Z103: =$B103*$B$67 -> 17.186448 | AA103: =$B103*$B$68 -> 16.709057 | AB103: =$B103*$B$69 -> 16.263299
A104: 2 | B104: =G74 -> 1868.7084 | C104: 0 | D104: =$B104*$B$44 -> 492.2676 | E104: =$B104*$B$45 -> 117.55233 | F104: =$B104*$B$46 -> 82.208008 | G104: =$B104*$B$47 -> 65.159517 | H104: =$B104*$B$48 -> 54.835912 | I104: =$B104*$B$49 -> 47.804722 | J104: =$B104*$B$50 -> 42.656129 | K104: =$B104*$B$51 -> 38.695628 | L104: =$B104*$B$52 -> 35.538181 | M104: =$B104*$B$53 -> 32.951712 | N104: =$B104*$B$54 -> 30.78733 | O104: =$B104*$B$55 -> 28.944758 | P104: =$B104*$B$56 -> 27.353787 | Q104: =$B104*$B$57 -> 25.963668 | R104: =$B104*$B$58 -> 24.736734 | S104: =$B104*$B$59 -> 23.644386 | T104: =$B104*$B$60 -> 22.66449 | U104: =$B104*$B$61 -> 21.779624 | V104: =$B104*$B$62 -> 20.975871 | W104: =$B104*$B$63 -> 20.24197 | X104: =$B104*$B$64 -> 19.568703 | Y104: =$B104*$B$65 -> 18.948442 | Z104: =$B104*$B$66 -> 18.374821 | AA104: =$B104*$B$67 -> 17.842478 | AB104: =$B104*$B$68 -> 17.346864
A105: 3 | B105: =G75 -> 1921.6249 | C105: 0 | D105: 0 | E105: =$B105*$B$44 -> 506.20722 | F105: =$B105*$B$45 -> 120.88108 | G105: =$B105*$B$46 -> 84.535904 | H105: =$B105*$B$47 -> 67.004648 | I105: =$B105*$B$48 -> 56.388709 | J105: =$B105*$B$49 -> 49.158415 | K105: =$B105*$B$50 -> 43.864029 | L105: =$B105*$B$51 -> 39.791378 | M105: =$B105*$B$52 -> 36.544521 | N105: =$B105*$B$53 -> 33.884811 | O105: =$B105*$B$54 -> 31.659139 | P105: =$B105*$B$55 -> 29.764391 | Q105: =$B105*$B$56 -> 28.128368 | R105: =$B105*$B$57 -> 26.698885 | S105: =$B105*$B$58 -> 25.437207 | T105: =$B105*$B$59 -> 24.313927 | U105: =$B105*$B$60 -> 23.306283 | V105: =$B105*$B$61 -> 22.39636 | W105: =$B105*$B$62 -> 21.569848 | X105: =$B105*$B$63 -> 20.815165 | Y105: =$B105*$B$64 -> 20.122832 | Z105: =$B105*$B$65 -> 19.485008 | AA105: =$B105*$B$66 -> 18.895143 | AB105: =$B105*$B$67 -> 18.347726
A106: 4 | B106: =G76 -> 2943.783 | C106: 0 | D106: 0 | E106: 0 | F106: =$B106*$B$44 -> 775.47091 | G106: =$B106*$B$45 -> 185.18061 | H106: =$B106*$B$46 -> 129.50257 | I106: =$B106*$B$47 -> 102.64602 | J106: =$B106*$B$48 -> 86.383208 | K106: =$B106*$B$49 -> 75.306949 | L106: =$B106*$B$50 -> 67.196352 | M106: =$B106*$B$51 -> 60.957361 | N106: =$B106*$B$52 -> 55.983423 | O106: =$B106*$B$53 -> 51.90895 | P106: =$B106*$B$54 -> 48.49939 | Q106: =$B106*$B$55 -> 45.59678 | R106: =$B106*$B$56 -> 43.090517 | S106: =$B106*$B$57 -> 40.900659 | T106: =$B106*$B$58 -> 38.967865 | U106: =$B106*$B$59 -> 37.247085 | V106: =$B106*$B$60 -> 35.703451 | W106: =$B106*$B$61 -> 34.309519 | X106: =$B106*$B$62 -> 33.043364 | Y106: =$B106*$B$63 -> 31.887248 | Z106: =$B106*$B$64 -> 30.826647 | AA106: =$B106*$B$65 -> 29.849548 | AB106: =$B106*$B$66 -> 28.945921
A107: 5 | B107: =G77 -> 2045.5659 | C107: 0 | D107: 0 | E107: 0 | F107: 0 | G107: =$B107*$B$44 -> 538.85658 | H107: =$B107*$B$45 -> 128.67767 | I107: =$B107*$B$46 -> 89.988302 | J107: =$B107*$B$47 -> 71.326315 | K107: =$B107*$B$48 -> 60.025669 | L107: =$B107*$B$49 -> 52.329036 | M107: =$B107*$B$50 -> 46.693172 | N107: =$B107*$B$51 -> 42.357843 | O107: =$B107*$B$52 -> 38.90157 | P107: =$B107*$B$53 -> 36.070314 | Q107: =$B107*$B$54 -> 33.701091 | R107: =$B107*$B$55 -> 31.684135 | S107: =$B107*$B$56 -> 29.942592 | T107: =$B107*$B$57 -> 28.42091 | U107: =$B107*$B$58 -> 27.077857 | V107: =$B107*$B$59 -> 25.882127 | W107: =$B107*$B$60 -> 24.809492 | X107: =$B107*$B$61 -> 23.840881 | Y107: =$B107*$B$62 -> 22.96106 | Z107: =$B107*$B$63 -> 22.157702 | AA107: =$B107*$B$64 -> 21.420715 | AB107: =$B107*$B$65 -> 20.741752
A108: 6 | B108: =G78 -> 2085.2387 | C108: 0 | D108: 0 | E108: 0 | F108: 0 | G108: 0 | H108: =$B108*$B$44 -> 549.30746 | I108: =$B108*$B$45 -> 131.17332 | J108: =$B108*$B$46 -> 91.733585 | K108: =$B108*$B$47 -> 72.709657 | L108: =$B108*$B$48 -> 61.18984 | M108: =$B108*$B$49 -> 53.343934 | N108: =$B108*$B$50 -> 47.598765 | O108: =$B108*$B$51 -> 43.179355 | P108: =$B108*$B$52 -> 39.656049 | Q108: =$B108*$B$53 -> 36.769882 | R108: =$B108*$B$54 -> 34.354709 | S108: =$B108*$B$55 -> 32.298635 | T108: =$B108*$B$56 -> 30.523315 | U108: =$B108*$B$57 -> 28.972121 | V108: =$B108*$B$58 -> 27.60302 | W108: =$B108*$B$59 -> 26.3841 | X108: =$B108*$B$60 -> 25.290662 | Y108: =$B108*$B$61 -> 24.303264 | Z108: =$B108*$B$62 -> 23.40638 | AA108: =$B108*$B$63 -> 22.587441 | AB108: =$B108*$B$64 -> 21.83616
A109: 7 | B109: =G79 -> 3185.3864 | C109: 0 | D109: 0 | E109: 0 | F109: 0 | G109: 0 | H109: 0 | I109: =$B109*$B$44 -> 839.11569 | J109: =$B109*$B$45 -> 200.37883 | K109: =$B109*$B$46 -> 140.13116 | L109: =$B109*$B$47 -> 111.07043 | M109: =$B109*$B$48 -> 93.472888 | N109: =$B109*$B$49 -> 81.487573 | O109: =$B109*$B$50 -> 72.71132 | P109: =$B109*$B$51 -> 65.96028 | Q109: =$B109*$B$52 -> 60.578119 | R109: =$B109*$B$53 -> 56.169243 | S109: =$B109*$B$54 -> 52.479853 | T109: =$B109*$B$55 -> 49.339019 | U109: =$B109*$B$56 -> 46.627061 | V109: =$B109*$B$57 -> 44.257476 | W109: =$B109*$B$58 -> 42.166052 | X109: =$B109*$B$59 -> 40.304044 | Y109: =$B109*$B$60 -> 38.63372 | Z109: =$B109*$B$61 -> 37.125384 | AA109: =$B109*$B$62 -> 35.755313 | AB109: =$B109*$B$63 -> 34.504312
A110: 8 | B110: =G80 -> 2222.7455 | C110: 0 | D110: 0 | E110: 0 | F110: 0 | G110: 0 | H110: 0 | I110: 0 | J110: =$B110*$B$44 -> 585.53042 | K110: =$B110*$B$45 -> 139.82327 | L110: =$B110*$B$46 -> 97.782769 | M110: =$B110*$B$47 -> 77.504347 | N110: =$B110*$B$48 -> 65.224879 | O110: =$B110*$B$49 -> 56.861591 | P110: =$B110*$B$50 -> 50.737568 | Q110: =$B110*$B$51 -> 46.026729 | R110: =$B110*$B$52 -> 42.271086 | S110: =$B110*$B$53 -> 39.194596 | T110: =$B110*$B$54 -> 36.62016 | U110: =$B110*$B$55 -> 34.428502 | V110: =$B110*$B$56 -> 32.536113 | W110: =$B110*$B$57 -> 30.882629 | X110: =$B110*$B$58 -> 29.423245 | Y110: =$B110*$B$59 -> 28.123945 | Z110: =$B110*$B$60 -> 26.958403 | AA110: =$B110*$B$61 -> 25.905894 | AB110: =$B110*$B$62 -> 24.949866
A111: 9 | B111: =G81 -> 2258.3771 | C111: 0 | D111: 0 | E111: 0 | F111: 0 | G111: 0 | H111: 0 | I111: 0 | J111: 0 | K111: =$B111*$B$44 -> 594.91673 | L111: =$B111*$B$45 -> 142.0647 | M111: =$B111*$B$46 -> 99.35027 | N111: =$B111*$B$47 -> 78.746776 | O111: =$B111*$B$48 -> 66.270462 | P111: =$B111*$B$49 -> 57.773107 | Q111: =$B111*$B$50 -> 51.550913 | R111: =$B111*$B$51 -> 46.764557 | S111: =$B111*$B$52 -> 42.94871 | T111: =$B111*$B$53 -> 39.822903 | U111: =$B111*$B$54 -> 37.207197 | V111: =$B111*$B$55 -> 34.980406 | W111: =$B111*$B$56 -> 33.057681 | X111: =$B111*$B$57 -> 31.377691 | Y111: =$B111*$B$58 -> 29.894912 | Z111: =$B111*$B$59 -> 28.574784 | AA111: =$B111*$B$60 -> 27.390557 | AB111: =$B111*$B$61 -> 26.321176
A112: 10 | B112: =G82 -> 3445.7249 | C112: 0 | D112: 0 | E112: 0 | F112: 0 | G112: 0 | H112: 0 | I112: 0 | J112: 0 | K112: 0 | L112: =$B112*$B$44 -> 907.69578 | M112: =$B112*$B$45 -> 216.7556 | N112: =$B112*$B$46 -> 151.58394 | O112: =$B112*$B$47 -> 120.1481 | P112: =$B112*$B$48 -> 101.11233 | Q112: =$B112*$B$49 -> 88.147472 | R112: =$B112*$B$50 -> 78.653944 | S112: =$B112*$B$51 -> 71.351148 | T112: =$B112*$B$52 -> 65.529108 | U112: =$B112*$B$53 -> 60.7599 | V112: =$B112*$B$54 -> 56.768979 | W112: =$B112*$B$55 -> 53.371448 | X112: =$B112*$B$56 -> 50.437844 | Y112: =$B112*$B$57 -> 47.874595 | Z112: =$B112*$B$58 -> 45.612242 | AA112: =$B112*$B$59 -> 43.598053 | AB112: =$B112*$B$60 -> 41.791216
A113: 11 | B113: =G83 -> 2413.6928 | C113: 0 | D113: 0 | E113: 0 | F113: 0 | G113: 0 | H113: 0 | I113: 0 | J113: 0 | K113: 0 | L113: 0 | M113: =$B113*$B$44 -> 635.83101 | N113: =$B113*$B$45 -> 151.83494 | O113: =$B113*$B$46 -> 106.1829 | P113: =$B113*$B$47 -> 84.162438 | Q113: =$B113*$B$48 -> 70.828089 | R113: =$B113*$B$49 -> 61.746344 | S113: =$B113*$B$50 -> 55.096231 | T113: =$B113*$B$51 -> 49.980702 | U113: =$B113*$B$52 -> 45.902427 | V113: =$B113*$B$53 -> 42.561648 | W113: =$B113*$B$54 -> 39.766052 | X113: =$B113*$B$55 -> 37.386118 | Y113: =$B113*$B$56 -> 35.331161 | Z113: =$B113*$B$57 -> 33.535633 | AA113: =$B113*$B$58 -> 31.950879 | AB113: =$B113*$B$59 -> 30.539962
A114: 12 | B114: =G84 -> 2445.5038 | C114: 0 | D114: 0 | E114: 0 | F114: 0 | G114: 0 | H114: 0 | I114: 0 | J114: 0 | K114: 0 | L114: 0 | M114: 0 | N114: =$B114*$B$44 -> 644.21089 | O114: =$B114*$B$45 -> 153.83603 | P114: =$B114*$B$46 -> 107.58233 | Q114: =$B114*$B$47 -> 85.271649 | R114: =$B114*$B$48 -> 71.761561 | S114: =$B114*$B$49 -> 62.560124 | T114: =$B114*$B$50 -> 55.822367 | U114: =$B114*$B$51 -> 50.639418 | V114: =$B114*$B$52 -> 46.507394 | W114: =$B114*$B$53 -> 43.122586 | X114: =$B114*$B$54 -> 40.290145 | Y114: =$B114*$B$55 -> 37.878845 | Z114: =$B114*$B$56 -> 35.796805 | AA114: =$B114*$B$57 -> 33.977612 | AB114: =$B114*$B$58 -> 32.371972
A115: 13 | B115: =G85 -> 3728.5411 | C115: 0 | D115: 0 | E115: 0 | F115: 0 | G115: 0 | H115: 0 | I115: 0 | J115: 0 | K115: 0 | L115: 0 | M115: 0 | N115: 0 | O115: =$B115*$B$44 -> 982.1971 | P115: =$B115*$B$45 -> 234.54634 | Q115: =$B115*$B$46 -> 164.02556 | R115: =$B115*$B$47 -> 130.00955 | S115: =$B115*$B$48 -> 109.41137 | T115: =$B115*$B$49 -> 95.382388 | U115: =$B115*$B$50 -> 85.109656 | V115: =$B115*$B$51 -> 77.207466 | W115: =$B115*$B$52 -> 70.907568 | X115: =$B115*$B$53 -> 65.746915 | Y115: =$B115*$B$54 -> 61.42843 | Z115: =$B115*$B$55 -> 57.752038 | AA115: =$B115*$B$56 -> 54.577652 | AB115: =$B115*$B$57 -> 51.804018
A116: 14 | B116: =G86 -> 2620.9274 | C116: 0 | D116: 0 | E116: 0 | F116: 0 | G116: 0 | H116: 0 | I116: 0 | J116: 0 | K116: 0 | L116: 0 | M116: 0 | N116: 0 | O116: 0 | P116: =$B116*$B$44 -> 690.42215 | Q116: =$B116*$B$45 -> 164.87117 | R116: =$B116*$B$46 -> 115.29954 | S116: =$B116*$B$47 -> 91.38845 | T116: =$B116*$B$48 -> 76.909242 | U116: =$B116*$B$49 -> 67.047757 | V116: =$B116*$B$50 -> 59.826679 | W116: =$B116*$B$51 -> 54.271942 | X116: =$B116*$B$52 -> 49.843514 | Y116: =$B116*$B$53 -> 46.215903 | Z116: =$B116*$B$54 -> 43.180283 | AA116: =$B116*$B$55 -> 40.596013 | AB116: =$B116*$B$56 -> 38.364621
A117: 15 | B117: =G87 -> 2648.8171 | C117: 0 | D117: 0 | E117: 0 | F117: 0 | G117: 0 | H117: 0 | I117: 0 | J117: 0 | K117: 0 | L117: 0 | M117: 0 | N117: 0 | O117: 0 | P117: 0 | Q117: =$B117*$B$44 -> 697.76902 | R117: =$B117*$B$45 -> 166.62558 | S117: =$B117*$B$46 -> 116.52646 | T117: =$B117*$B$47 -> 92.360927 | U117: =$B117*$B$48 -> 77.727643 | V117: =$B117*$B$49 -> 67.761221 | W117: =$B117*$B$50 -> 60.463303 | X117: =$B117*$B$51 -> 54.849457 | Y117: =$B117*$B$52 -> 50.373905 | Z117: =$B117*$B$53 -> 46.707693 | AA117: =$B117*$B$54 -> 43.63977 | AB117: =$B117*$B$55 -> 41.028
A118: 16 | B118: =G88 -> 4036.5795 | C118: 0 | D118: 0 | E118: 0 | F118: 0 | G118: 0 | H118: 0 | I118: 0 | J118: 0 | K118: 0 | L118: 0 | M118: 0 | N118: 0 | O118: 0 | P118: 0 | Q118: 0 | R118: =$B118*$B$44 -> 1063.3426 | S118: =$B118*$B$45 -> 253.92369 | T118: =$B118*$B$46 -> 177.57675 | U118: =$B118*$B$47 -> 140.75046 | V118: =$B118*$B$48 -> 118.45054 | W118: =$B118*$B$49 -> 103.26253 | X118: =$B118*$B$50 -> 92.141103 | Y118: =$B118*$B$51 -> 83.586063 | Z118: =$B118*$B$52 -> 76.765691 | AA118: =$B118*$B$53 -> 71.178684 | AB118: =$B118*$B$54 -> 66.503422
A119: 17 | B119: =G89 -> 2846.4427 | C119: 0 | D119: 0 | E119: 0 | F119: 0 | G119: 0 | H119: 0 | I119: 0 | J119: 0 | K119: 0 | L119: 0 | M119: 0 | N119: 0 | O119: 0 | P119: 0 | Q119: 0 | R119: 0 | S119: =$B119*$B$44 -> 749.82888 | T119: =$B119*$B$45 -> 179.05736 | U119: =$B119*$B$46 -> 125.22038 | V119: =$B119*$B$47 -> 99.251885 | W119: =$B119*$B$48 -> 83.526826 | X119: =$B119*$B$49 -> 72.816819 | Y119: =$B119*$B$50 -> 64.97441 | Z119: =$B119*$B$51 -> 58.941721 | AA119: =$B119*$B$52 -> 54.132253 | AB119: =$B119*$B$53 -> 50.192508
...

Sheet Heat maps
A1: Heat maps: when money comes in, and where play time goes
A2: Top: planned timing of each purchase (blue) turned into revenue by player age (heat). Bottom: planned share of play time by feature. Replace with tracked data after launch.
A4: When purchases happen (each row adds up to 100%)
A5: Product | B5: Your cash, first 30 days (USD) | C5: Day 0 (first session) | D5: Days 1-2 | E5: Days 3-6 | F5: Week 2 | G5: Weeks 3-4 | H5: Check
A6: Debut Pack (fixed contents, no randomness) | B6: =Revenue!N18 -> 3.9501 | C6: 0.7 | D6: 0.25 | E6: 0.05 | F6: 0 | G6: 0 | H6: =IF(ROUND(SUM(C6:G6),6)=1,"OK","Must add up to 100%") -> OK
A7: Auto-Stream | B7: =Revenue!N19 -> 5.2934 | C7: 0 | D7: 0.45 | E7: 0.3 | F7: 0.15 | G7: 0.1 | H7: =IF(ROUND(SUM(C7:G7),6)=1,"OK","Must add up to 100%") -> OK
A8: 2x Hype | B8: =Revenue!N20 -> 2.97255 | C8: 0 | D8: 0.4 | E8: 0.3 | F8: 0.18 | G8: 0.12 | H8: =IF(ROUND(SUM(C8:G8),6)=1,"OK","Must add up to 100%") -> OK
A9: 3x Open | B9: =Revenue!N21 -> 2.9639715 | C9: 0 | D9: 0.4 | E9: 0.3 | F9: 0.18 | G9: 0.12 | H9: =IF(ROUND(SUM(C9:G9),6)=1,"OK","Must add up to 100%") -> OK
A10: Offline earnings 24h | B10: =Revenue!N22 -> 1.486275 | C10: 0 | D10: 0.3 | E10: 0.35 | F10: 0.2 | G10: 0.15 | H10: =IF(ROUND(SUM(C10:G10),6)=1,"OK","Must add up to 100%") -> OK
A11: Gem bundle (average) | B11: =Revenue!N23 -> 22.274424 | C11: 0 | D11: 0.2 | E11: 0.25 | F11: 0.27 | G11: 0.28 | H11: =IF(ROUND(SUM(C11:G11),6)=1,"OK","Must add up to 100%") -> OK
A12: Luck potion | B12: =Revenue!N24 -> 2.333086 | C12: 0 | D12: 0.25 | E12: 0.25 | F12: 0.22 | G12: 0.28 | H12: =IF(ROUND(SUM(C12:G12),6)=1,"OK","Must add up to 100%") -> OK
A13: Card shop: pick the exact card (no randomness) | B13: =Revenue!N25 -> 5.96505 | C13: 0 | D13: 0.15 | E13: 0.25 | F13: 0.3 | G13: 0.3 | H13: =IF(ROUND(SUM(C13:G13),6)=1,"OK","Must add up to 100%") -> OK
A14: 8x Open | B14: =Revenue!N26 -> 4.5652303 | C14: 0 | D14: 0 | E14: 0 | F14: 0.55 | G14: 0.45 | H14: =IF(ROUND(SUM(C14:G14),6)=1,"OK","Must add up to 100%") -> OK
A15: Lucky | B15: =Revenue!N27 -> 2.6587658 | C15: 0 | D15: 0 | E15: 0 | F15: 0.5 | G15: 0.5 | H15: =IF(ROUND(SUM(C15:G15),6)=1,"OK","Must add up to 100%") -> OK
A16: +1 Squad Slot | B16: =Revenue!N28 -> 2.545088 | C16: 0 | D16: 0 | E16: 0 | F16: 0.5 | G16: 0.5 | H16: =IF(ROUND(SUM(C16:G16),6)=1,"OK","Must add up to 100%") -> OK
A17: VIP | B17: =Revenue!N29 -> 2.123744 | C17: 0 | D17: 0 | E17: 0 | F17: 0.45 | G17: 0.55 | H17: =IF(ROUND(SUM(C17:G17),6)=1,"OK","Must add up to 100%") -> OK
... A22: Cosmetics (outfits, skins, emotes) | B22: =Revenue!N34 -> 3.17072 | C22: 0 | D22: 0 | E22: 0 | F22: 0.45 | G22: 0.55 | H22: =IF(ROUND(SUM(C22:G22),6)=1,"OK","Must add up to 100%") -> OK
A23: Fan Club subscription | B23: =Revenue!B44 -> 3.992 | C23: 0 | D23: 0 | E23: 0 | F23: 0.6 | G23: 0.4 | H23: =IF(ROUND(SUM(C23:G23),6)=1,"OK","Must add up to 100%") -> OK
A25: Revenue heat map: your cash by product and player age (USD)
A26: Product | B26: Total | C26: Day 0 (first session) | D26: Days 1-2 | E26: Days 3-6 | F26: Week 2 | G26: Weeks 3-4
A27: Debut Pack (fixed contents, no randomness) | B27: =SUM(C27:G27) -> 3.9501 | C27: =$B6*C6 -> 2.76507 | D27: =$B6*D6 -> 0.987525 | E27: =$B6*E6 -> 0.197505 | F27: =$B6*F6 -> 0 | G27: =$B6*G6 -> 0
A28: Auto-Stream | B28: =SUM(C28:G28) -> 5.2934 | C28: =$B7*C7 -> 0 | D28: =$B7*D7 -> 2.38203 | E28: =$B7*E7 -> 1.58802 | F28: =$B7*F7 -> 0.79401 | G28: =$B7*G7 -> 0.52934
A29: 2x Hype | B29: =SUM(C29:G29) -> 2.97255 | C29: =$B8*C8 -> 0 | D29: =$B8*D8 -> 1.18902 | E29: =$B8*E8 -> 0.891765 | F29: =$B8*F8 -> 0.535059 | G29: =$B8*G8 -> 0.356706
A30: 3x Open | B30: =SUM(C30:G30) -> 2.9639715 | C30: =$B9*C9 -> 0 | D30: =$B9*D9 -> 1.1855886 | E30: =$B9*E9 -> 0.88919145 | F30: =$B9*F9 -> 0.53351487 | G30: =$B9*G9 -> 0.35567658
A31: Offline earnings 24h | B31: =SUM(C31:G31) -> 1.486275 | C31: =$B10*C10 -> 0 | D31: =$B10*D10 -> 0.4458825 | E31: =$B10*E10 -> 0.52019625 | F31: =$B10*F10 -> 0.297255 | G31: =$B10*G10 -> 0.22294125
A32: Gem bundle (average) | B32: =SUM(C32:G32) -> 22.274424 | C32: =$B11*C11 -> 0 | D32: =$B11*D11 -> 4.4548849 | E32: =$B11*E11 -> 5.5686061 | F32: =$B11*F11 -> 6.0140946 | G32: =$B11*G11 -> 6.2368388
A33: Luck potion | B33: =SUM(C33:G33) -> 2.333086 | C33: =$B12*C12 -> 0 | D33: =$B12*D12 -> 0.5832715 | E33: =$B12*E12 -> 0.5832715 | F33: =$B12*F12 -> 0.51327892 | G33: =$B12*G12 -> 0.65326408
A34: Card shop: pick the exact card (no randomness) | B34: =SUM(C34:G34) -> 5.96505 | C34: =$B13*C13 -> 0 | D34: =$B13*D13 -> 0.8947575 | E34: =$B13*E13 -> 1.4912625 | F34: =$B13*F13 -> 1.789515 | G34: =$B13*G13 -> 1.789515
A35: 8x Open | B35: =SUM(C35:G35) -> 4.5652303 | C35: =$B14*C14 -> 0 | D35: =$B14*D14 -> 0 | E35: =$B14*E14 -> 0 | F35: =$B14*F14 -> 2.5108767 | G35: =$B14*G14 -> 2.0543536
A36: Lucky | B36: =SUM(C36:G36) -> 2.6587658 | C36: =$B15*C15 -> 0 | D36: =$B15*D15 -> 0 | E36: =$B15*E15 -> 0 | F36: =$B15*F15 -> 1.3293829 | G36: =$B15*G15 -> 1.3293829
A37: +1 Squad Slot | B37: =SUM(C37:G37) -> 2.545088 | C37: =$B16*C16 -> 0 | D37: =$B16*D16 -> 0 | E37: =$B16*E16 -> 0 | F37: =$B16*F16 -> 1.272544 | G37: =$B16*G16 -> 1.272544
A38: VIP | B38: =SUM(C38:G38) -> 2.123744 | C38: =$B17*C17 -> 0 | D38: =$B17*D17 -> 0 | E38: =$B17*E17 -> 0 | F38: =$B17*F17 -> 0.9556848 | G38: =$B17*G17 -> 1.1680592
... A44: Fan Club subscription | B44: =SUM(C44:G44) -> 3.992 | C44: =$B23*C23 -> 0 | D44: =$B23*D23 -> 0 | E44: =$B23*E23 -> 0 | F44: =$B23*F23 -> 2.3952 | G44: =$B23*G23 -> 1.5968
A45: Total | B45: =SUM(B27:B44) -> 78.132097 | C45: =SUM(C27:C44) -> 2.76507 | D45: =SUM(D27:D44) -> 12.12296 | E45: =SUM(E27:E44) -> 11.729818 | F45: =SUM(F27:F44) -> 25.528768 | G45: =SUM(G27:G44) -> 25.985481
A46: Share of 30-day revenue | C46: =IF($B$45=0,0,C45/$B$45) -> 0.035389681 | D46: =IF($B$45=0,0,D45/$B$45) -> 0.15515979 | E46: =IF($B$45=0,0,E45/$B$45) -> 0.15012803 | F46: =IF($B$45=0,0,F45/$B$45) -> 0.32673855 | G46: =IF($B$45=0,0,G45/$B$45) -> 0.33258395
A47: If most money arrives in weeks 2-4, retention matters more than better first-session offers.
A49: Where play time goes as players age (planned share of play time, each column adds up to 100%)
A50: Feature | B50: Minutes 0-5 | C50: Rest of first session | D50: Days 2-3 | E50: Days 4-7 | F50: Weeks 2-4 | G50: Month 2+
A51: Streaming (clicking) and Fever | B51: 0.55 | C51: 0.3 | D51: 0.18 | E51: 0.12 | F51: 0.08 | G51: 0.06
A52: Pack opening | B52: 0.25 | C52: 0.2 | D52: 0.15 | E52: 0.12 | F52: 0.1 | G52: 0.08
A53: Boss fights and stages | B53: 0.1 | C53: 0.25 | D53: 0.22 | E53: 0.18 | F53: 0.14 | G53: 0.12
A54: Binder and fusion | B54: 0.05 | C54: 0.1 | D54: 0.12 | E54: 0.12 | F54: 0.12 | G54: 0.1
A55: Skill tree | B55: 0 | C55: 0 | D55: 0.08 | E55: 0.08 | F55: 0.07 | G55: 0.06
A56: Daily quests and attendance | B56: 0 | C56: 0.05 | D56: 0.08 | E56: 0.08 | F56: 0.07 | G56: 0.06
A57: Fandom war | B57: 0 | C57: 0 | D57: 0.05 | E57: 0.1 | F57: 0.1 | G57: 0.1
A58: Comeback events | B58: 0 | C58: 0 | D58: 0.04 | E58: 0.06 | F58: 0.12 | G58: 0.14
A59: Social hub and showcase stage | B59: 0.05 | C59: 0.05 | D59: 0.05 | E59: 0.06 | F59: 0.06 | G59: 0.08
A60: Trading | B60: 0 | C60: 0 | D60: 0 | E60: 0 | F60: 0.06 | G60: 0.1
A61: New Era rebirth | B61: 0 | C61: 0 | D61: 0 | E61: 0.05 | F61: 0.04 | G61: 0.06
A62: Live concerts and Album Drop (co-op) | B62: 0 | C62: 0.05 | D62: 0.03 | E62: 0.03 | F62: 0.04 | G62: 0.04
A63: Check | B63: =IF(ROUND(SUM(B51:B62),6)=1,"OK","Must add up to 100%") -> OK | C63: =IF(ROUND(SUM(C51:C62),6)=1,"OK","Must add up to 100%") -> OK | D63: =IF(ROUND(SUM(D51:D62),6)=1,"OK","Must add up to 100%") -> OK | E63: =IF(ROUND(SUM(E51:E62),6)=1,"OK","Must add up to 100%") -> OK | F63: =IF(ROUND(SUM(F51:F62),6)=1,"OK","Must add up to 100%") -> OK | G63: =IF(ROUND(SUM(G51:G62),6)=1,"OK","Must add up to 100%") -> OK
A64: Biggest share of play time | B64: =INDEX($A$51:$A$62,MATCH(MAX(B51:B62),B51:B62,0)) -> Streaming (clicking) and Fever | C64: =INDEX($A$51:$A$62,MATCH(MAX(C51:C62),C51:C62,0)) -> Streaming (clicking) and Fever | D64: =INDEX($A$51:$A$62,MATCH(MAX(D51:D62),D51:D62,0)) -> Boss fights and stages | E64: =INDEX($A$51:$A$62,MATCH(MAX(E51:E62),E51:E62,0)) -> Boss fights and stages | F64: =INDEX($A$51:$A$62,MATCH(MAX(F51:F62),F51:F62,0)) -> Boss fights and stages | G64: =INDEX($A$51:$A$62,MATCH(MAX(G51:G62),G51:G62,0)) -> Comeback events
A65: Features with 10%+ of play time | B65: =COUNTIF(B51:B62,">=0.1") -> 3 | C65: =COUNTIF(C51:C62,">=0.1") -> 4 | D65: =COUNTIF(D51:D62,">=0.1") -> 4 | E65: =COUNTIF(E51:E62,">=0.1") -> 5 | F65: =COUNTIF(F51:F62,">=0.1") -> 5 | G65: =COUNTIF(G51:G62,">=0.1") -> 5
A66: Rule of thumb for this plan: every stage should have a new feature climbing, and after the first session no single feature should take most of the time.

Sheet Tracking
A1: Tracking plan: log these so the model and heat maps fill with real data
A2: All methods are on AnalyticsService (Roblox Creator Docs). Store each player's first-join date and send "days since first join" with every event.
A4: Event | B4: When to log it | C4: AnalyticsService method | D4: What to include | E4: What it tells you (tab)
A5: Onboarding steps | B5: Each first: joined, first click, first Fever, first pack, named group, first boss win, reached Busking Street, hit first wall | C5: LogOnboardingFunnelStepEvent | D5: step number and name | E5: Where new players quit; first-play bounce (Pacing)
A6: Zone reached | B6: Entering each zone | C6: LogProgressionCompleteEvent | D6: path "Zones", level = zone number, zone name | E6: Real arrival times vs. the model (Pacing)
A7: Boss attempts | B7: Start, fail and win of each boss | C7: LogProgressionStartEvent / FailEvent / CompleteEvent | D7: boss level and name | E7: Which walls stop players (Pacing)
A8: Gems earned and spent | B8: Every gem change | C8: LogEconomyEvent | D8: Source or Sink, "Gems", amount, ending balance, transaction type (Quest, Drop, Pack, Shop), item SKU | E8: Real free gems per day; days to pity (Gems)
A9: Hype earned and spent | B9: Batched once a minute, not per click | C9: LogEconomyEvent | D9: Source or Sink, "Hype", amount, ending balance | E9: Real Hype per second (Pacing)
A10: Pack opened | B10: Every pull | C10: LogCustomEvent "PackOpened" | D10: rarity, version (Holo/Signed), pity count, boost on or off | E10: Real drop rates match the posted odds (Odds)
A11: Purchase | B11: After each successful Robux purchase | C11: LogCustomEvent "Purchase" | D11: value = Robux price; product, days since first join, zone | E11: Real revenue heat map by product and player age (Heat maps)
A12: Shop visit | B12: Open shop, view item, purchase prompt, bought | C12: LogFunnelStepEvent "Shop" | D12: one funnel session ID per visit, step | E12: Which offers convert and where buyers drop (Revenue)
A13: Feature time | B13: When a player leaves a feature (batched) | C13: LogCustomEvent "FeatureTime" | D13: value = seconds; feature name, days since first join | E13: Real play-time heat map (Heat maps)
A14: Playing with friends | B14: While a friend is in the same server | C14: LogCustomEvent "PlayWithFriend" | D14: value = minutes together | E14: Co-play, a discovery signal (Growth)
A15: Comeback return | B15: First join during a comeback | C15: LogCustomEvent "ComebackJoin" | D15: days since last visit | E15: How many lapsed players a comeback wins back (Growth)
A16: Session recap | B16: When the end-of-session recap shows | C16: LogCustomEvent "SessionRecap" | D16: value = session minutes | E16: Whether sessions end on a high, and next-day return
